{
"meta":{"test_sets":[],"test_metrics":[],"learn_metrics":[{"best_value":"Min","name":"RMSE"}],"launch_mode":"Train","parameters":"","iteration_count":1000,"learn_sets":["learn"],"name":"experiment"},
"iterations":[
{"learn":[17.03004087],"iteration":0,"passed_time":0.0474074465,"remaining_time":47.36003906},
{"learn":[16.85056758],"iteration":1,"passed_time":0.08071172699,"remaining_time":40.27515177},
{"learn":[16.6329533],"iteration":2,"passed_time":0.1145629371,"remaining_time":38.07308278},
{"learn":[16.44141856],"iteration":3,"passed_time":0.1479147002,"remaining_time":36.83076034},
{"learn":[16.26675481],"iteration":4,"passed_time":0.1818891972,"remaining_time":36.19595024},
{"learn":[16.0721934],"iteration":5,"passed_time":0.2169501375,"remaining_time":35.94140611},
{"learn":[15.88168405],"iteration":6,"passed_time":0.2525775266,"remaining_time":35.82992628},
{"learn":[15.7202921],"iteration":7,"passed_time":0.2864568715,"remaining_time":35.52065206},
{"learn":[15.55903746],"iteration":8,"passed_time":0.3204464734,"remaining_time":35.28471724},
{"learn":[15.3901185],"iteration":9,"passed_time":0.3548468832,"remaining_time":35.12984144},
{"learn":[15.21847004],"iteration":10,"passed_time":0.3894351338,"remaining_time":35.01375885},
{"learn":[15.09060023],"iteration":11,"passed_time":0.4239273881,"remaining_time":34.90335495},
{"learn":[14.93525203],"iteration":12,"passed_time":0.4599982532,"remaining_time":34.92448276},
{"learn":[14.79370731],"iteration":13,"passed_time":0.4950457328,"remaining_time":34.86536375},
{"learn":[14.64260336],"iteration":14,"passed_time":0.5299143355,"remaining_time":34.79770803},
{"learn":[14.50359253],"iteration":15,"passed_time":0.5638887797,"remaining_time":34.67915995},
{"learn":[14.37372046],"iteration":16,"passed_time":0.5982208893,"remaining_time":34.59124318},
{"learn":[14.24087528],"iteration":17,"passed_time":0.6337176969,"remaining_time":34.57282102},
{"learn":[14.10079175],"iteration":18,"passed_time":0.6702127341,"remaining_time":34.60414169},
{"learn":[13.9983907],"iteration":19,"passed_time":0.7044313745,"remaining_time":34.51713735},
{"learn":[13.89590493],"iteration":20,"passed_time":0.7391870462,"remaining_time":34.4601961},
{"learn":[13.78035922],"iteration":21,"passed_time":0.7733476587,"remaining_time":34.37881864},
{"learn":[13.67595625],"iteration":22,"passed_time":0.8081877267,"remaining_time":34.33040909},
{"learn":[13.57508971],"iteration":23,"passed_time":0.8426939073,"remaining_time":34.26955223},
{"learn":[13.48268259],"iteration":24,"passed_time":0.8771794514,"remaining_time":34.20999861},
{"learn":[13.38771768],"iteration":25,"passed_time":0.9139025255,"remaining_time":34.23619461},
{"learn":[13.27385938],"iteration":26,"passed_time":0.9482546036,"remaining_time":34.17228627},
{"learn":[13.16089015],"iteration":27,"passed_time":0.9834653092,"remaining_time":34.14029574},
{"learn":[13.08121762],"iteration":28,"passed_time":1.01772367,"remaining_time":34.076196},
{"learn":[12.97473852],"iteration":29,"passed_time":1.053040401,"remaining_time":34.04830629},
{"learn":[12.87327844],"iteration":30,"passed_time":1.087884541,"remaining_time":34.00516517},
{"learn":[12.7708485],"iteration":31,"passed_time":1.123000516,"remaining_time":33.9707656},
{"learn":[12.67781115],"iteration":32,"passed_time":1.160038288,"remaining_time":33.9926371},
{"learn":[12.58596595],"iteration":33,"passed_time":1.19525375,"remaining_time":33.9592683},
{"learn":[12.4885234],"iteration":34,"passed_time":1.229524339,"remaining_time":33.89974248},
{"learn":[12.39998621],"iteration":35,"passed_time":1.264740412,"remaining_time":33.86693771},
{"learn":[12.33445576],"iteration":36,"passed_time":1.29976056,"remaining_time":33.82890324},
{"learn":[12.25402281],"iteration":37,"passed_time":1.334866797,"remaining_time":33.79320682},
{"learn":[12.18295252],"iteration":38,"passed_time":1.370737197,"remaining_time":33.77637042},
{"learn":[12.1245793],"iteration":39,"passed_time":1.404943735,"remaining_time":33.71864963},
{"learn":[12.06220524],"iteration":40,"passed_time":1.439565999,"remaining_time":33.67179983},
{"learn":[11.98462881],"iteration":41,"passed_time":1.473710521,"remaining_time":33.61463521},
{"learn":[11.90611277],"iteration":42,"passed_time":1.507837956,"remaining_time":33.55816102},
{"learn":[11.84304428],"iteration":43,"passed_time":1.542103468,"remaining_time":33.50570263},
{"learn":[11.7802161],"iteration":44,"passed_time":1.577901797,"remaining_time":33.48658257},
{"learn":[11.72693567],"iteration":45,"passed_time":1.612871019,"remaining_time":33.44954244},
{"learn":[11.67022778],"iteration":46,"passed_time":1.648481889,"remaining_time":33.42560086},
{"learn":[11.58928478],"iteration":47,"passed_time":1.682336051,"remaining_time":33.36633169},
{"learn":[11.53117801],"iteration":48,"passed_time":1.716911078,"remaining_time":33.32209052},
{"learn":[11.46421243],"iteration":49,"passed_time":1.751205913,"remaining_time":33.27291234},
{"learn":[11.4135361],"iteration":50,"passed_time":1.787046525,"remaining_time":33.25308141},
{"learn":[11.3545643],"iteration":51,"passed_time":1.822564889,"remaining_time":33.2267599},
{"learn":[11.30188097],"iteration":52,"passed_time":1.857364961,"remaining_time":33.18725694},
{"learn":[11.23451121],"iteration":53,"passed_time":1.891732635,"remaining_time":33.14035319},
{"learn":[11.18783543],"iteration":54,"passed_time":1.93103805,"remaining_time":33.17874468},
{"learn":[11.13941526],"iteration":55,"passed_time":1.965820113,"remaining_time":33.13811047},
{"learn":[11.09324765],"iteration":56,"passed_time":2.000511647,"remaining_time":33.09618391},
{"learn":[11.03904848],"iteration":57,"passed_time":2.038186505,"remaining_time":33.10296013},
{"learn":[10.99256577],"iteration":58,"passed_time":2.075457203,"remaining_time":33.10178352},
{"learn":[10.94543698],"iteration":59,"passed_time":2.112950929,"remaining_time":33.10289789},
{"learn":[10.88720248],"iteration":60,"passed_time":2.151749859,"remaining_time":33.122838},
{"learn":[10.83830027],"iteration":61,"passed_time":2.189198161,"remaining_time":33.1204496},
{"learn":[10.79513554],"iteration":62,"passed_time":2.226433377,"remaining_time":33.11377895},
{"learn":[10.73312606],"iteration":63,"passed_time":2.26501006,"remaining_time":33.12577212},
{"learn":[10.67935085],"iteration":64,"passed_time":2.30128174,"remaining_time":33.10305272},
{"learn":[10.62504217],"iteration":65,"passed_time":2.337758307,"remaining_time":33.0828221},
{"learn":[10.57590273],"iteration":66,"passed_time":2.373021083,"remaining_time":33.04520403},
{"learn":[10.53349342],"iteration":67,"passed_time":2.408355879,"remaining_time":33.00864234},
{"learn":[10.48645754],"iteration":68,"passed_time":2.445896253,"remaining_time":33.00187554},
{"learn":[10.44482886],"iteration":69,"passed_time":2.482848786,"remaining_time":32.98641958},
{"learn":[10.39666085],"iteration":70,"passed_time":2.518828527,"remaining_time":32.9576296},
{"learn":[10.35700937],"iteration":71,"passed_time":2.5554179,"remaining_time":32.93649737},
{"learn":[10.32191813],"iteration":72,"passed_time":2.592495698,"remaining_time":32.921144},
{"learn":[10.29143232],"iteration":73,"passed_time":2.627399173,"remaining_time":32.87799506},
{"learn":[10.24956676],"iteration":74,"passed_time":2.665255038,"remaining_time":32.8714788},
{"learn":[10.21228975],"iteration":75,"passed_time":2.703603306,"remaining_time":32.87012441},
{"learn":[10.16226395],"iteration":76,"passed_time":2.740609805,"remaining_time":32.85172532},
{"learn":[10.12267253],"iteration":77,"passed_time":2.778256546,"remaining_time":32.84041712},
{"learn":[10.08212382],"iteration":78,"passed_time":2.814120121,"remaining_time":32.80765356},
{"learn":[10.04946958],"iteration":79,"passed_time":2.850381091,"remaining_time":32.77938255},
{"learn":[10.01572],"iteration":80,"passed_time":2.886880863,"remaining_time":32.75362362},
{"learn":[9.985418061],"iteration":81,"passed_time":2.936296952,"remaining_time":32.87220246},
{"learn":[9.94280973],"iteration":82,"passed_time":2.972383323,"remaining_time":32.83946394},
{"learn":[9.914939469],"iteration":83,"passed_time":3.00707084,"remaining_time":32.79139154},
{"learn":[9.871242481],"iteration":84,"passed_time":3.043000107,"remaining_time":32.75700115},
{"learn":[9.847212928],"iteration":85,"passed_time":3.078226594,"remaining_time":32.7151059},
{"learn":[9.821400802],"iteration":86,"passed_time":3.114883488,"remaining_time":32.688375},
{"learn":[9.793618211],"iteration":87,"passed_time":3.151415496,"remaining_time":32.66012423},
{"learn":[9.763101271],"iteration":88,"passed_time":3.189046279,"remaining_time":32.64293439},
{"learn":[9.733059775],"iteration":89,"passed_time":3.224328244,"remaining_time":32.60154114},
{"learn":[9.712572602],"iteration":90,"passed_time":3.260251829,"remaining_time":32.56669135},
{"learn":[9.683702907],"iteration":91,"passed_time":3.29778116,"remaining_time":32.54766624},
{"learn":[9.666037766],"iteration":92,"passed_time":3.334160035,"remaining_time":32.51702314},
{"learn":[9.638704953],"iteration":93,"passed_time":3.372026122,"remaining_time":32.50059219},
{"learn":[9.611881431],"iteration":94,"passed_time":3.408780903,"remaining_time":32.47312334},
{"learn":[9.579096856],"iteration":95,"passed_time":3.445662032,"remaining_time":32.44665081},
{"learn":[9.533595888],"iteration":96,"passed_time":3.482538451,"remaining_time":32.41991981},
{"learn":[9.497529742],"iteration":97,"passed_time":3.520636524,"remaining_time":32.40422596},
{"learn":[9.467702433],"iteration":98,"passed_time":3.556958581,"remaining_time":32.37191598},
{"learn":[9.445775482],"iteration":99,"passed_time":3.595862028,"remaining_time":32.36275825},
{"learn":[9.429716933],"iteration":100,"passed_time":3.6317237,"remaining_time":32.3259367},
{"learn":[9.402092995],"iteration":101,"passed_time":3.667441159,"remaining_time":32.28786432},
{"learn":[9.376803556],"iteration":102,"passed_time":3.704609548,"remaining_time":32.26247345},
{"learn":[9.344590832],"iteration":103,"passed_time":3.740752615,"remaining_time":32.22802253},
{"learn":[9.334481573],"iteration":104,"passed_time":3.777846021,"remaining_time":32.20163989},
{"learn":[9.301179924],"iteration":105,"passed_time":3.815644968,"remaining_time":32.18100567},
{"learn":[9.274602208],"iteration":106,"passed_time":3.852186102,"remaining_time":32.14955317},
{"learn":[9.260344872],"iteration":107,"passed_time":3.888520212,"remaining_time":32.11629656},
{"learn":[9.225289792],"iteration":108,"passed_time":3.925730389,"remaining_time":32.09014474},
{"learn":[9.19933274],"iteration":109,"passed_time":3.962341794,"remaining_time":32.05894724},
{"learn":[9.17615006],"iteration":110,"passed_time":4.000213501,"remaining_time":32.03774597},
{"learn":[9.147275152],"iteration":111,"passed_time":4.03653236,"remaining_time":32.00393514},
{"learn":[9.116346157],"iteration":112,"passed_time":4.072859034,"remaining_time":31.97014127},
{"learn":[9.104102049],"iteration":113,"passed_time":4.108652561,"remaining_time":31.93215938},
{"learn":[9.077607693],"iteration":114,"passed_time":4.144068119,"remaining_time":31.89130683},
{"learn":[9.044329554],"iteration":115,"passed_time":4.180266455,"remaining_time":31.85651333},
{"learn":[9.017428119],"iteration":116,"passed_time":4.216772576,"remaining_time":31.82401867},
{"learn":[8.995697626],"iteration":117,"passed_time":4.253617261,"remaining_time":31.79398665},
{"learn":[8.977505349],"iteration":118,"passed_time":4.289133267,"remaining_time":31.75400343},
{"learn":[8.953250063],"iteration":119,"passed_time":4.32521342,"remaining_time":31.71823175},
{"learn":[8.935112005],"iteration":120,"passed_time":4.360915379,"remaining_time":31.67970759},
{"learn":[8.911816152],"iteration":121,"passed_time":4.396887499,"remaining_time":31.64317397},
{"learn":[8.893882492],"iteration":122,"passed_time":4.43511613,"remaining_time":31.62273859},
{"learn":[8.86671322],"iteration":123,"passed_time":4.471967258,"remaining_time":31.59228482},
{"learn":[8.846080175],"iteration":124,"passed_time":4.508751326,"remaining_time":31.56125928},
{"learn":[8.825053774],"iteration":125,"passed_time":4.545470945,"remaining_time":31.52969528},
{"learn":[8.811834999],"iteration":126,"passed_time":4.582442732,"remaining_time":31.4997835},
{"learn":[8.792878159],"iteration":127,"passed_time":4.61875641,"remaining_time":31.46527805},
{"learn":[8.762746705],"iteration":128,"passed_time":4.655145861,"remaining_time":31.43125616},
{"learn":[8.740271495],"iteration":129,"passed_time":4.693065262,"remaining_time":31.40743675},
{"learn":[8.70919304],"iteration":130,"passed_time":4.729930026,"remaining_time":31.37640605},
{"learn":[8.690032779],"iteration":131,"passed_time":4.767062174,"remaining_time":31.34704521},
{"learn":[8.675786488],"iteration":132,"passed_time":4.803771876,"remaining_time":31.31481366},
{"learn":[8.661697487],"iteration":133,"passed_time":4.83954887,"remaining_time":31.27648747},
{"learn":[8.635981673],"iteration":134,"passed_time":4.877265713,"remaining_time":31.25062846},
{"learn":[8.611913224],"iteration":135,"passed_time":4.915029833,"remaining_time":31.22489541},
{"learn":[8.596336071],"iteration":136,"passed_time":4.952792376,"remaining_time":31.19897679},
{"learn":[8.574122278],"iteration":137,"passed_time":4.9890775,"remaining_time":31.16365801},
{"learn":[8.556324758],"iteration":138,"passed_time":5.025765305,"remaining_time":31.13081962},
{"learn":[8.532771694],"iteration":139,"passed_time":5.062736124,"remaining_time":31.09966476},
{"learn":[8.511814917],"iteration":140,"passed_time":5.097956469,"remaining_time":31.05776317},
{"learn":[8.493030581],"iteration":141,"passed_time":5.134587122,"remaining_time":31.02447712},
{"learn":[8.4731083],"iteration":142,"passed_time":5.17176449,"remaining_time":30.99442076},
{"learn":[8.453197827],"iteration":143,"passed_time":5.20700682,"remaining_time":30.95276276},
{"learn":[8.430264458],"iteration":144,"passed_time":5.242338862,"remaining_time":30.91172226},
{"learn":[8.415149069],"iteration":145,"passed_time":5.27889754,"remaining_time":30.87793492},
{"learn":[8.385720874],"iteration":146,"passed_time":5.316999317,"remaining_time":30.85306407},
{"learn":[8.36638184],"iteration":147,"passed_time":5.366295464,"remaining_time":30.89245767},
{"learn":[8.334613449],"iteration":148,"passed_time":5.40376726,"remaining_time":30.8631271},
{"learn":[8.314876697],"iteration":149,"passed_time":5.44110257,"remaining_time":30.83291456},
{"learn":[8.294820552],"iteration":150,"passed_time":5.47726179,"remaining_time":30.7959951},
{"learn":[8.275933839],"iteration":151,"passed_time":5.512399556,"remaining_time":30.753387},
{"learn":[8.268700159],"iteration":152,"passed_time":5.551582504,"remaining_time":30.73327046},
{"learn":[8.255333279],"iteration":153,"passed_time":5.591065625,"remaining_time":30.71455532},
{"learn":[8.241775523],"iteration":154,"passed_time":5.627797406,"remaining_time":30.68057295},
{"learn":[8.225952165],"iteration":155,"passed_time":5.665542666,"remaining_time":30.65203853},
{"learn":[8.207172235],"iteration":156,"passed_time":5.701979836,"remaining_time":30.61636307},
{"learn":[8.187561661],"iteration":157,"passed_time":5.74095946,"remaining_time":30.59422699},
{"learn":[8.17015356],"iteration":158,"passed_time":5.779035302,"remaining_time":30.56709867},
{"learn":[8.140736116],"iteration":159,"passed_time":5.814784162,"remaining_time":30.52761685},
{"learn":[8.124830625],"iteration":160,"passed_time":5.850468836,"remaining_time":30.48784692},
{"learn":[8.10851644],"iteration":161,"passed_time":5.885877687,"remaining_time":30.44670063},
{"learn":[8.093953098],"iteration":162,"passed_time":5.922084757,"remaining_time":30.40972357},
{"learn":[8.083124164],"iteration":163,"passed_time":5.959940219,"remaining_time":30.38115868},
{"learn":[8.06188643],"iteration":164,"passed_time":5.995131708,"remaining_time":30.33899986},
{"learn":[8.042824302],"iteration":165,"passed_time":6.033812591,"remaining_time":30.31445603},
{"learn":[8.017767737],"iteration":166,"passed_time":6.069706285,"remaining_time":30.27584033},
{"learn":[7.995319767],"iteration":167,"passed_time":6.106837668,"remaining_time":30.24338654},
{"learn":[7.968553908],"iteration":168,"passed_time":6.142950136,"remaining_time":30.20586724},
{"learn":[7.953736727],"iteration":169,"passed_time":6.179603001,"remaining_time":30.17100289},
{"learn":[7.942954227],"iteration":170,"passed_time":6.216499319,"remaining_time":30.13729787},
{"learn":[7.929503493],"iteration":171,"passed_time":6.253953633,"remaining_time":30.10624191},
{"learn":[7.920149376],"iteration":172,"passed_time":6.290428044,"remaining_time":30.0704277},
{"learn":[7.904951095],"iteration":173,"passed_time":6.326191022,"remaining_time":30.03122865},
{"learn":[7.898920939],"iteration":174,"passed_time":6.362728052,"remaining_time":29.99571796},
{"learn":[7.889856699],"iteration":175,"passed_time":6.400898959,"remaining_time":29.96784513},
{"learn":[7.86984017],"iteration":176,"passed_time":6.437726577,"remaining_time":29.93361002},
{"learn":[7.846585041],"iteration":177,"passed_time":6.475945594,"remaining_time":29.90577123},
{"learn":[7.823206898],"iteration":178,"passed_time":6.512386033,"remaining_time":29.86965884},
{"learn":[7.808824827],"iteration":179,"passed_time":6.548101883,"remaining_time":29.83024191},
{"learn":[7.801718055],"iteration":180,"passed_time":6.584167177,"remaining_time":29.79244706},
{"learn":[7.798693748],"iteration":181,"passed_time":6.619957008,"remaining_time":29.75343315},
{"learn":[7.775595741],"iteration":182,"passed_time":6.655410739,"remaining_time":29.71295396},
{"learn":[7.758383971],"iteration":183,"passed_time":6.69408284,"remaining_time":29.68680216},
{"learn":[7.739434051],"iteration":184,"passed_time":6.728957134,"remaining_time":29.64378413},
{"learn":[7.722705775],"iteration":185,"passed_time":6.765181798,"remaining_time":29.60676335},
{"learn":[7.696096331],"iteration":186,"passed_time":6.800343711,"remaining_time":29.56513068},
{"learn":[7.689287883],"iteration":187,"passed_time":6.835459703,"remaining_time":29.5233685},
{"learn":[7.685097581],"iteration":188,"passed_time":6.871587638,"remaining_time":29.48601891},
{"learn":[7.661633293],"iteration":189,"passed_time":6.909409557,"remaining_time":29.4559039},
{"learn":[7.643940342],"iteration":190,"passed_time":6.946834056,"remaining_time":29.42402488},
{"learn":[7.620299078],"iteration":191,"passed_time":6.983575705,"remaining_time":29.38921443},
{"learn":[7.6060733],"iteration":192,"passed_time":7.020365308,"remaining_time":29.35458448},
{"learn":[7.601683384],"iteration":193,"passed_time":7.056275416,"remaining_time":29.31627827},
{"learn":[7.583664932],"iteration":194,"passed_time":7.092531077,"remaining_time":29.27942316},
{"learn":[7.56913714],"iteration":195,"passed_time":7.131425228,"remaining_time":29.25339737},
{"learn":[7.561957441],"iteration":196,"passed_time":7.166746581,"remaining_time":29.21267769},
{"learn":[7.548061691],"iteration":197,"passed_time":7.201828516,"remaining_time":29.17104278},
{"learn":[7.534688344],"iteration":198,"passed_time":7.238113158,"remaining_time":29.13431477},
{"learn":[7.518545762],"iteration":199,"passed_time":7.274630661,"remaining_time":29.09852264},
{"learn":[7.502975384],"iteration":200,"passed_time":7.310990831,"remaining_time":29.06209788},
{"learn":[7.497490846],"iteration":201,"passed_time":7.348716993,"remaining_time":29.0310701},
{"learn":[7.485451761],"iteration":202,"passed_time":7.385839983,"remaining_time":28.99760821},
{"learn":[7.472190857],"iteration":203,"passed_time":7.426999279,"remaining_time":28.97985993},
{"learn":[7.453377287],"iteration":204,"passed_time":7.464221611,"remaining_time":28.94661552},
{"learn":[7.432769252],"iteration":205,"passed_time":7.501492557,"remaining_time":28.91351986},
{"learn":[7.415765003],"iteration":206,"passed_time":7.539043285,"remaining_time":28.88145567},
{"learn":[7.401720222],"iteration":207,"passed_time":7.582232381,"remaining_time":28.87080791},
{"learn":[7.39456943],"iteration":208,"passed_time":7.616654817,"remaining_time":28.82666967},
{"learn":[7.373005503],"iteration":209,"passed_time":7.652326999,"remaining_time":28.78732538},
{"learn":[7.359182826],"iteration":210,"passed_time":7.68768727,"remaining_time":28.74684955},
{"learn":[7.335725142],"iteration":211,"passed_time":7.723494873,"remaining_time":28.70808472},
{"learn":[7.316122958],"iteration":212,"passed_time":7.759422539,"remaining_time":28.66979126},
{"learn":[7.303125002],"iteration":213,"passed_time":7.79728758,"remaining_time":28.63863569},
{"learn":[7.291393739],"iteration":214,"passed_time":7.834132676,"remaining_time":28.60369372},
{"learn":[7.283541265],"iteration":215,"passed_time":7.869372135,"remaining_time":28.56290627},
{"learn":[7.271291044],"iteration":216,"passed_time":7.903850296,"remaining_time":28.51942296},
{"learn":[7.24651621],"iteration":217,"passed_time":7.939851837,"remaining_time":28.48148687},
{"learn":[7.24016082],"iteration":218,"passed_time":7.977311134,"remaining_time":28.4487671},
{"learn":[7.208606596],"iteration":219,"passed_time":8.016506236,"remaining_time":28.42215847},
{"learn":[7.185083043],"iteration":220,"passed_time":8.054267359,"remaining_time":28.39038132},
{"learn":[7.17313458],"iteration":221,"passed_time":8.090941546,"remaining_time":28.35474109},
{"learn":[7.148614499],"iteration":222,"passed_time":8.127676426,"remaining_time":28.31930306},
{"learn":[7.13123865],"iteration":223,"passed_time":8.163916098,"remaining_time":28.28213791},
{"learn":[7.115781388],"iteration":224,"passed_time":8.199954878,"remaining_time":28.24428902},
{"learn":[7.096856499],"iteration":225,"passed_time":8.236494107,"remaining_time":28.20817008},
{"learn":[7.079472175],"iteration":226,"passed_time":8.270919988,"remaining_time":28.16485089},
{"learn":[7.051708606],"iteration":227,"passed_time":8.322599812,"remaining_time":28.18003094},
{"learn":[7.021026021],"iteration":228,"passed_time":8.358884207,"remaining_time":28.14279355},
{"learn":[7.000273949],"iteration":229,"passed_time":8.396132218,"remaining_time":28.10879047},
{"learn":[6.979746997],"iteration":230,"passed_time":8.435644456,"remaining_time":28.08229691},
{"learn":[6.962432541],"iteration":231,"passed_time":8.472316287,"remaining_time":28.0462884},
{"learn":[6.943312974],"iteration":232,"passed_time":8.509316375,"remaining_time":28.01135476},
{"learn":[6.922775641],"iteration":233,"passed_time":8.546382227,"remaining_time":27.97661874},
{"learn":[6.915571121],"iteration":234,"passed_time":8.582987138,"remaining_time":27.94036239},
{"learn":[6.909869714],"iteration":235,"passed_time":8.619405234,"remaining_time":27.9034983},
{"learn":[6.904715358],"iteration":236,"passed_time":8.655978403,"remaining_time":27.86713722},
{"learn":[6.880334099],"iteration":237,"passed_time":8.691903133,"remaining_time":27.82869827},
{"learn":[6.875045161],"iteration":238,"passed_time":8.72828718,"remaining_time":27.79174286},
{"learn":[6.869436036],"iteration":239,"passed_time":8.763171262,"remaining_time":27.75004233},
{"learn":[6.853419179],"iteration":240,"passed_time":8.799078764,"remaining_time":27.7116215},
{"learn":[6.833637097],"iteration":241,"passed_time":8.835808378,"remaining_time":27.67579649},
{"learn":[6.814961213],"iteration":242,"passed_time":8.872472537,"remaining_time":27.63976012},
{"learn":[6.800170456],"iteration":243,"passed_time":8.910371512,"remaining_time":27.60754452},
{"learn":[6.78822785],"iteration":244,"passed_time":8.947300112,"remaining_time":27.57229218},
{"learn":[6.769183723],"iteration":245,"passed_time":8.983339406,"remaining_time":27.53430046},
{"learn":[6.763797268],"iteration":246,"passed_time":9.021048484,"remaining_time":27.50141501},
{"learn":[6.737689627],"iteration":247,"passed_time":9.057068958,"remaining_time":27.46337039},
{"learn":[6.710604155],"iteration":248,"passed_time":9.094680663,"remaining_time":27.43014128},
{"learn":[6.694672023],"iteration":249,"passed_time":9.131456833,"remaining_time":27.3943705},
{"learn":[6.690291413],"iteration":250,"passed_time":9.165916956,"remaining_time":27.35168048},
{"learn":[6.662669607],"iteration":251,"passed_time":9.20120909,"remaining_time":27.3115254},
{"learn":[6.657809821],"iteration":252,"passed_time":9.237323666,"remaining_time":27.27383707},
{"learn":[6.652348615],"iteration":253,"passed_time":9.271886776,"remaining_time":27.23160447},
{"learn":[6.631139753],"iteration":254,"passed_time":9.309026293,"remaining_time":27.19695917},
{"learn":[6.626529047],"iteration":255,"passed_time":9.346762398,"remaining_time":27.16402822},
{"learn":[6.610341256],"iteration":256,"passed_time":9.383082536,"remaining_time":27.12696624},
{"learn":[6.606303691],"iteration":257,"passed_time":9.419719727,"remaining_time":27.09082185},
{"learn":[6.595470827],"iteration":258,"passed_time":9.453872058,"remaining_time":27.04756446},
{"learn":[6.591596261],"iteration":259,"passed_time":9.488741912,"remaining_time":27.00641929},
{"learn":[6.57153702],"iteration":260,"passed_time":9.526005377,"remaining_time":26.97209951},
{"learn":[6.55685298],"iteration":261,"passed_time":9.563934426,"remaining_time":26.93963208},
{"learn":[6.53421599],"iteration":262,"passed_time":9.599539412,"remaining_time":26.90061044},
{"learn":[6.520551077],"iteration":263,"passed_time":9.63636243,"remaining_time":26.86501041},
{"learn":[6.517201878],"iteration":264,"passed_time":9.670614048,"remaining_time":26.82226915},
{"learn":[6.512942141],"iteration":265,"passed_time":9.705853585,"remaining_time":26.78231779},
{"learn":[6.498051731],"iteration":266,"passed_time":9.743262301,"remaining_time":26.7483568},
{"learn":[6.482338969],"iteration":267,"passed_time":9.779680498,"remaining_time":26.71166465},
{"learn":[6.474623654],"iteration":268,"passed_time":9.815182932,"remaining_time":26.67248596},
{"learn":[6.458258146],"iteration":269,"passed_time":9.850655423,"remaining_time":26.63325355},
{"learn":[6.44585658],"iteration":270,"passed_time":9.887705536,"remaining_time":26.59829275},
{"learn":[6.429601008],"iteration":271,"passed_time":9.925200023,"remaining_time":26.56450594},
{"learn":[6.412758443],"iteration":272,"passed_time":9.960141989,"remaining_time":26.5238946},
{"learn":[6.400162424],"iteration":273,"passed_time":9.998524808,"remaining_time":26.49244164},
{"learn":[6.383575452],"iteration":274,"passed_time":10.03544091,"remaining_time":26.4570715},
{"learn":[6.369189936],"iteration":275,"passed_time":10.07148034,"remaining_time":26.41939047},
{"learn":[6.365646259],"iteration":276,"passed_time":10.10712211,"remaining_time":26.38068335},
{"learn":[6.361810656],"iteration":277,"passed_time":10.1434364,"remaining_time":26.34374489},
{"learn":[6.35824538],"iteration":278,"passed_time":10.17982818,"remaining_time":26.30701117},
{"learn":[6.340000378],"iteration":279,"passed_time":10.21741276,"remaining_time":26.27334709},
{"learn":[6.321783024],"iteration":280,"passed_time":10.25433279,"remaining_time":26.23795471},
{"learn":[6.298681036],"iteration":281,"passed_time":10.29000609,"remaining_time":26.19937722},
{"learn":[6.280822295],"iteration":282,"passed_time":10.3276773,"remaining_time":26.16588206},
{"learn":[6.27217703],"iteration":283,"passed_time":10.36407714,"remaining_time":26.12915222},
{"learn":[6.266632154],"iteration":284,"passed_time":10.39957832,"remaining_time":26.09017017},
{"learn":[6.25711764],"iteration":285,"passed_time":10.43819188,"remaining_time":26.05898252},
{"learn":[6.242062711],"iteration":286,"passed_time":10.47499781,"remaining_time":26.0232524},
{"learn":[6.228780741],"iteration":287,"passed_time":10.51230382,"remaining_time":25.98875111},
{"learn":[6.225544725],"iteration":288,"passed_time":10.54935585,"remaining_time":25.95360556},
{"learn":[6.22240763],"iteration":289,"passed_time":10.58552721,"remaining_time":25.91629075},
{"learn":[6.210371735],"iteration":290,"passed_time":10.62140468,"remaining_time":25.87826776},
{"learn":[6.190816627],"iteration":291,"passed_time":10.66025141,"remaining_time":25.8474589},
{"learn":[6.187347196],"iteration":292,"passed_time":10.69482359,"remaining_time":25.80628081},
{"learn":[6.184621163],"iteration":293,"passed_time":10.73104198,"remaining_time":25.76910082},
{"learn":[6.169346989],"iteration":294,"passed_time":10.76672771,"remaining_time":25.73065435},
{"learn":[6.14894411],"iteration":295,"passed_time":10.8032531,"remaining_time":25.6942236},
{"learn":[6.135765844],"iteration":296,"passed_time":10.84052427,"remaining_time":25.65955745},
{"learn":[6.117949093],"iteration":297,"passed_time":10.88094974,"remaining_time":25.63230443},
{"learn":[6.11244797],"iteration":298,"passed_time":10.91843557,"remaining_time":25.59807135},
{"learn":[6.103001541],"iteration":299,"passed_time":10.95497976,"remaining_time":25.56161944},
{"learn":[6.100688809],"iteration":300,"passed_time":10.99009747,"remaining_time":25.52185425},
{"learn":[6.088502374],"iteration":301,"passed_time":11.02484593,"remaining_time":25.48126641},
{"learn":[6.068527494],"iteration":302,"passed_time":11.06226445,"remaining_time":25.44685915},
{"learn":[6.055777662],"iteration":303,"passed_time":11.09814422,"remaining_time":25.40890914},
{"learn":[6.052704497],"iteration":304,"passed_time":11.13560582,"remaining_time":25.37457719},
{"learn":[6.044158018],"iteration":305,"passed_time":11.17259421,"remaining_time":25.33915158},
{"learn":[6.030987456],"iteration":306,"passed_time":11.20917613,"remaining_time":25.30279824},
{"learn":[6.012432293],"iteration":307,"passed_time":11.24492169,"remaining_time":25.26456432},
{"learn":[5.999244365],"iteration":308,"passed_time":11.28210621,"remaining_time":25.22956437},
{"learn":[5.980206791],"iteration":309,"passed_time":11.31855516,"remaining_time":25.1929131},
{"learn":[5.968882869],"iteration":310,"passed_time":11.35563269,"remaining_time":25.15765571},
{"learn":[5.953668239],"iteration":311,"passed_time":11.39375462,"remaining_time":25.12468967},
{"learn":[5.940054406],"iteration":312,"passed_time":11.42991027,"remaining_time":25.08737494},
{"learn":[5.935326789],"iteration":313,"passed_time":11.46535242,"remaining_time":25.0485088},
{"learn":[5.928152322],"iteration":314,"passed_time":11.5027614,"remaining_time":25.01394145},
{"learn":[5.910575783],"iteration":315,"passed_time":11.53977492,"remaining_time":24.97850014},
{"learn":[5.897194428],"iteration":316,"passed_time":11.57606195,"remaining_time":24.94148364},
{"learn":[5.887921942],"iteration":317,"passed_time":11.61169495,"remaining_time":24.90306904},
{"learn":[5.885132076],"iteration":318,"passed_time":11.64717191,"remaining_time":24.86433878},
{"learn":[5.87704171],"iteration":319,"passed_time":11.68270507,"remaining_time":24.82574828},
{"learn":[5.865196091],"iteration":320,"passed_time":11.71875849,"remaining_time":24.7882773},
{"learn":[5.848044137],"iteration":321,"passed_time":11.75746552,"remaining_time":24.75640256},
{"learn":[5.844073565],"iteration":322,"passed_time":11.79313832,"remaining_time":24.71812582},
{"learn":[5.829191185],"iteration":323,"passed_time":11.83000431,"remaining_time":24.68235467},
{"learn":[5.812694704],"iteration":324,"passed_time":11.86578082,"remaining_time":24.644314},
{"learn":[5.810414846],"iteration":325,"passed_time":11.9033642,"remaining_time":24.61002291},
{"learn":[5.799712815],"iteration":326,"passed_time":11.94057159,"remaining_time":24.57493787},
{"learn":[5.791220714],"iteration":327,"passed_time":11.9767345,"remaining_time":24.53769995},
{"learn":[5.775025828],"iteration":328,"passed_time":12.01346571,"remaining_time":24.50162763},
{"learn":[5.758859824],"iteration":329,"passed_time":12.05187671,"remaining_time":24.46896181},
{"learn":[5.755258029],"iteration":330,"passed_time":12.0886862,"remaining_time":24.43302438},
{"learn":[5.752301611],"iteration":331,"passed_time":12.12574046,"remaining_time":24.39757417},
{"learn":[5.735907097],"iteration":332,"passed_time":12.1626213,"remaining_time":24.36176699},
{"learn":[5.727367252],"iteration":333,"passed_time":12.20045618,"remaining_time":24.32785574},
{"learn":[5.709141957],"iteration":334,"passed_time":12.23788487,"remaining_time":24.29311475},
{"learn":[5.695044704],"iteration":335,"passed_time":12.27390405,"remaining_time":24.2555723},
{"learn":[5.682017617],"iteration":336,"passed_time":12.31032322,"remaining_time":24.21882581},
{"learn":[5.676832435],"iteration":337,"passed_time":12.34431179,"remaining_time":24.17732072},
{"learn":[5.661392115],"iteration":338,"passed_time":12.38043079,"remaining_time":24.14001402},
{"learn":[5.657744632],"iteration":339,"passed_time":12.41593455,"remaining_time":24.10152001},
{"learn":[5.649371749],"iteration":340,"passed_time":12.44983721,"remaining_time":24.05994933},
{"learn":[5.632050668],"iteration":341,"passed_time":12.48470318,"remaining_time":24.02027688},
{"learn":[5.629264213],"iteration":342,"passed_time":12.51839111,"remaining_time":23.97837598},
{"learn":[5.614818284],"iteration":343,"passed_time":12.55286831,"remaining_time":23.93802794},
{"learn":[5.611602913],"iteration":344,"passed_time":12.58713409,"remaining_time":23.89731255},
{"learn":[5.596822828],"iteration":345,"passed_time":12.62309504,"remaining_time":23.8598386},
{"learn":[5.578520139],"iteration":346,"passed_time":12.66017762,"remaining_time":23.82448411},
{"learn":[5.570159805],"iteration":347,"passed_time":12.69798226,"remaining_time":23.79047252},
{"learn":[5.554105046],"iteration":348,"passed_time":12.7360208,"remaining_time":23.75687548},
{"learn":[5.540312374],"iteration":349,"passed_time":12.77527074,"remaining_time":23.72550281},
{"learn":[5.535318791],"iteration":350,"passed_time":12.81523141,"remaining_time":23.69539939},
{"learn":[5.527846226],"iteration":351,"passed_time":12.85342371,"remaining_time":23.66198455},
{"learn":[5.520592255],"iteration":352,"passed_time":12.89200277,"remaining_time":23.62925154},
{"learn":[5.506003683],"iteration":353,"passed_time":12.9306815,"remaining_time":23.59666736},
{"learn":[5.503892433],"iteration":354,"passed_time":12.96838349,"remaining_time":23.56227423},
{"learn":[5.487496146],"iteration":355,"passed_time":13.00677642,"remaining_time":23.5291124},
{"learn":[5.484864604],"iteration":356,"passed_time":13.04565633,"remaining_time":23.49679838},
{"learn":[5.467601826],"iteration":357,"passed_time":13.08519947,"remaining_time":23.46563704},
{"learn":[5.460450694],"iteration":358,"passed_time":13.1233336,"remaining_time":23.43191319},
{"learn":[5.451040076],"iteration":359,"passed_time":13.16073376,"remaining_time":23.39686001},
{"learn":[5.437219634],"iteration":360,"passed_time":13.19776069,"remaining_time":23.36113319},
{"learn":[5.423270386],"iteration":361,"passed_time":13.23568899,"remaining_time":23.32698778},
{"learn":[5.406622324],"iteration":362,"passed_time":13.27502511,"remaining_time":23.29529199},
{"learn":[5.405088414],"iteration":363,"passed_time":13.314186,"remaining_time":23.26324806},
{"learn":[5.394685261],"iteration":364,"passed_time":13.3531959,"remaining_time":23.23090245},
{"learn":[5.39252277],"iteration":365,"passed_time":13.39108687,"remaining_time":23.19658218},
{"learn":[5.389870226],"iteration":366,"passed_time":13.44001433,"remaining_time":23.18127812},
{"learn":[5.382069155],"iteration":367,"passed_time":13.48142739,"remaining_time":23.15288618},
{"learn":[5.380760081],"iteration":368,"passed_time":13.52440054,"remaining_time":23.12709143},
{"learn":[5.369043083],"iteration":369,"passed_time":13.56386234,"remaining_time":23.09522506},
{"learn":[5.367039447],"iteration":370,"passed_time":13.60013294,"remaining_time":23.05790733},
{"learn":[5.358252878],"iteration":371,"passed_time":13.63918457,"remaining_time":23.02529008},
{"learn":[5.341893116],"iteration":372,"passed_time":13.67916684,"remaining_time":22.99420271},
{"learn":[5.337039644],"iteration":373,"passed_time":13.71878737,"remaining_time":22.96246228},
{"learn":[5.327191604],"iteration":374,"passed_time":13.75689568,"remaining_time":22.92815947},
{"learn":[5.31962128],"iteration":375,"passed_time":13.79347622,"remaining_time":22.89130097},
{"learn":[5.307852743],"iteration":376,"passed_time":13.83175309,"remaining_time":22.85724714},
{"learn":[5.305600364],"iteration":377,"passed_time":13.86786425,"remaining_time":22.81960731},
{"learn":[5.301032997],"iteration":378,"passed_time":13.9127635,"remaining_time":22.79637503},
{"learn":[5.290162882],"iteration":379,"passed_time":13.95485461,"remaining_time":22.768447},
{"learn":[5.288421618],"iteration":380,"passed_time":13.99225819,"remaining_time":22.73282893},
{"learn":[5.279829888],"iteration":381,"passed_time":14.02692744,"remaining_time":22.6927779},
{"learn":[5.267819827],"iteration":382,"passed_time":14.06043526,"remaining_time":22.65088396},
{"learn":[5.264292047],"iteration":383,"passed_time":14.09701933,"remaining_time":22.61396851},
{"learn":[5.255555444],"iteration":384,"passed_time":14.1351357,"remaining_time":22.57950248},
{"learn":[5.253309974],"iteration":385,"passed_time":14.17299466,"remaining_time":22.54460808},
{"learn":[5.245052221],"iteration":386,"passed_time":14.20767447,"remaining_time":22.50466265},
{"learn":[5.233904102],"iteration":387,"passed_time":14.24200854,"remaining_time":22.46419903},
{"learn":[5.222021013],"iteration":388,"passed_time":14.27617826,"remaining_time":22.42350878},
{"learn":[5.221176201],"iteration":389,"passed_time":14.30981516,"remaining_time":22.38201858},
{"learn":[5.211735347],"iteration":390,"passed_time":14.3442551,"remaining_time":22.34181932},
{"learn":[5.202460333],"iteration":391,"passed_time":14.37878603,"remaining_time":22.30179058},
{"learn":[5.18959532],"iteration":392,"passed_time":14.41607433,"remaining_time":22.26604865},
{"learn":[5.176242141],"iteration":393,"passed_time":14.45082642,"remaining_time":22.226398},
{"learn":[5.163344158],"iteration":394,"passed_time":14.48561187,"remaining_time":22.18682325},
{"learn":[5.160407973],"iteration":395,"passed_time":14.51897493,"remaining_time":22.14510318},
{"learn":[5.153949771],"iteration":396,"passed_time":14.5535896,"remaining_time":22.10532626},
{"learn":[5.141320786],"iteration":397,"passed_time":14.58832892,"remaining_time":22.06576384},
{"learn":[5.13247215],"iteration":398,"passed_time":14.62240618,"remaining_time":22.02522836},
{"learn":[5.121793577],"iteration":399,"passed_time":14.65825429,"remaining_time":21.98738143},
{"learn":[5.108789105],"iteration":400,"passed_time":14.69305912,"remaining_time":21.94798607},
{"learn":[5.095454482],"iteration":401,"passed_time":14.72808099,"remaining_time":21.90893639},
{"learn":[5.09301307],"iteration":402,"passed_time":14.76160751,"remaining_time":21.86769152},
{"learn":[5.082085399],"iteration":403,"passed_time":14.79692372,"remaining_time":21.8291251},
{"learn":[5.080454617],"iteration":404,"passed_time":14.83128727,"remaining_time":21.78917512},
{"learn":[5.076970374],"iteration":405,"passed_time":14.8652881,"remaining_time":21.74872201},
{"learn":[5.070840543],"iteration":406,"passed_time":14.90189833,"remaining_time":21.71210249},
{"learn":[5.06245305],"iteration":407,"passed_time":14.93797125,"remaining_time":21.67470339},
{"learn":[5.060778472],"iteration":408,"passed_time":14.97177812,"remaining_time":21.63403636},
{"learn":[5.059862883],"iteration":409,"passed_time":15.00695848,"remaining_time":21.59537928},
{"learn":[5.051248831],"iteration":410,"passed_time":15.04088193,"remaining_time":21.55493785},
{"learn":[5.049845895],"iteration":411,"passed_time":15.0750225,"remaining_time":21.51483794},
{"learn":[5.045901556],"iteration":412,"passed_time":15.11054912,"remaining_time":21.47673689},
{"learn":[5.043302086],"iteration":413,"passed_time":15.14443133,"remaining_time":21.43632067},
{"learn":[5.034121449],"iteration":414,"passed_time":15.17858314,"remaining_time":21.396316},
{"learn":[5.033048077],"iteration":415,"passed_time":15.21220254,"remaining_time":21.35559203},
{"learn":[5.020104901],"iteration":416,"passed_time":15.24736501,"remaining_time":21.31705948},
{"learn":[5.018338333],"iteration":417,"passed_time":15.28120258,"remaining_time":21.27669833},
{"learn":[5.017128038],"iteration":418,"passed_time":15.31626384,"remaining_time":21.23806514},
{"learn":[5.004783911],"iteration":419,"passed_time":15.35103844,"remaining_time":21.19905308},
{"learn":[5.002607627],"iteration":420,"passed_time":15.38479985,"remaining_time":21.15866773},
{"learn":[4.997529592],"iteration":421,"passed_time":15.41891056,"remaining_time":21.11879218},
{"learn":[4.988092949],"iteration":422,"passed_time":15.45377957,"remaining_time":21.07997828},
{"learn":[4.977720851],"iteration":423,"passed_time":15.48834475,"remaining_time":21.04077023},
{"learn":[4.976012051],"iteration":424,"passed_time":15.52344842,"remaining_time":21.00231257},
{"learn":[4.967995872],"iteration":425,"passed_time":15.55844662,"remaining_time":20.96372855},
{"learn":[4.958161826],"iteration":426,"passed_time":15.59344969,"remaining_time":20.92516785},
{"learn":[4.948564673],"iteration":427,"passed_time":15.62768121,"remaining_time":20.88559264},
{"learn":[4.938144654],"iteration":428,"passed_time":15.66494814,"remaining_time":20.85008249},
{"learn":[4.931211909],"iteration":429,"passed_time":15.70003938,"remaining_time":20.81168011},
{"learn":[4.921764492],"iteration":430,"passed_time":15.73704341,"remaining_time":20.77581833},
{"learn":[4.915700921],"iteration":431,"passed_time":15.771628,"remaining_time":20.73677014},
{"learn":[4.905349559],"iteration":432,"passed_time":15.80650882,"remaining_time":20.69813049},
{"learn":[4.904516048],"iteration":433,"passed_time":15.8404624,"remaining_time":20.6582989},
{"learn":[4.893933118],"iteration":434,"passed_time":15.8755444,"remaining_time":20.61995996},
{"learn":[4.890659695],"iteration":435,"passed_time":15.91116263,"remaining_time":20.58232965},
{"learn":[4.884100532],"iteration":436,"passed_time":15.9482121,"remaining_time":20.54655243},
{"learn":[4.875915932],"iteration":437,"passed_time":15.98228877,"remaining_time":20.506955},
{"learn":[4.865567777],"iteration":438,"passed_time":16.01870239,"remaining_time":20.47036911},
{"learn":[4.861892815],"iteration":439,"passed_time":16.05303717,"remaining_time":20.43113821},
{"learn":[4.855392022],"iteration":440,"passed_time":16.08770368,"remaining_time":20.39235001},
{"learn":[4.842802767],"iteration":441,"passed_time":16.12261288,"remaining_time":20.35388684},
{"learn":[4.835722386],"iteration":442,"passed_time":16.15867902,"remaining_time":20.31689439},
{"learn":[4.829127654],"iteration":443,"passed_time":16.19313035,"remaining_time":20.27788395},
{"learn":[4.823044444],"iteration":444,"passed_time":16.22700132,"remaining_time":20.23817019},
{"learn":[4.818275623],"iteration":445,"passed_time":16.26103183,"remaining_time":20.19868079},
{"learn":[4.816495155],"iteration":446,"passed_time":16.29481639,"remaining_time":20.15891155},
{"learn":[4.810813584],"iteration":447,"passed_time":16.32874673,"remaining_time":20.11934865},
{"learn":[4.80974298],"iteration":448,"passed_time":16.36455938,"remaining_time":20.08212075},
{"learn":[4.801607641],"iteration":449,"passed_time":16.40074752,"remaining_time":20.04535808},
{"learn":[4.791993248],"iteration":450,"passed_time":16.43735511,"remaining_time":20.00910854},
{"learn":[4.786120752],"iteration":451,"passed_time":16.47537989,"remaining_time":19.97457562},
{"learn":[4.784966081],"iteration":452,"passed_time":16.51150702,"remaining_time":19.93773585},
{"learn":[4.77830107],"iteration":453,"passed_time":16.54634414,"remaining_time":19.8993478},
{"learn":[4.770185041],"iteration":454,"passed_time":16.58050996,"remaining_time":19.86017127},
{"learn":[4.765876752],"iteration":455,"passed_time":16.61801393,"remaining_time":19.82499907},
{"learn":[4.757372417],"iteration":456,"passed_time":16.65583262,"remaining_time":19.79019062},
{"learn":[4.750763631],"iteration":457,"passed_time":16.69228165,"remaining_time":19.75374816},
{"learn":[4.742642773],"iteration":458,"passed_time":16.7268922,"remaining_time":19.71513874},
{"learn":[4.73536844],"iteration":459,"passed_time":16.76419794,"remaining_time":19.67971063},
{"learn":[4.727183046],"iteration":460,"passed_time":16.80135578,"remaining_time":19.64410145},
{"learn":[4.715992823],"iteration":461,"passed_time":16.83686501,"remaining_time":19.60656575},
{"learn":[4.709249978],"iteration":462,"passed_time":16.87152637,"remaining_time":19.56805542},
{"learn":[4.707703227],"iteration":463,"passed_time":16.90848025,"remaining_time":19.53220994},
{"learn":[4.697236188],"iteration":464,"passed_time":16.94599581,"remaining_time":19.49700593},
{"learn":[4.694568861],"iteration":465,"passed_time":16.98159488,"remaining_time":19.45959585},
{"learn":[4.693216594],"iteration":466,"passed_time":17.01910561,"remaining_time":19.42437536},
{"learn":[4.684027743],"iteration":467,"passed_time":17.0571243,"remaining_time":19.3897225},
{"learn":[4.676439896],"iteration":468,"passed_time":17.09178641,"remaining_time":19.35125498},
{"learn":[4.667280349],"iteration":469,"passed_time":17.12655256,"remaining_time":19.31292097},
{"learn":[4.658841789],"iteration":470,"passed_time":17.16090755,"remaining_time":19.27414033},
{"learn":[4.654576567],"iteration":471,"passed_time":17.19525381,"remaining_time":19.23536867},
{"learn":[4.653169964],"iteration":472,"passed_time":17.23045526,"remaining_time":19.19756855},
{"learn":[4.648598577],"iteration":473,"passed_time":17.26988489,"remaining_time":19.16447142},
{"learn":[4.640089905],"iteration":474,"passed_time":17.30825888,"remaining_time":19.13018086},
{"learn":[4.62835241],"iteration":475,"passed_time":17.34726282,"remaining_time":19.09656663},
{"learn":[4.627078916],"iteration":476,"passed_time":17.38433611,"remaining_time":19.06081297},
{"learn":[4.621574432],"iteration":477,"passed_time":17.41908257,"remaining_time":19.02251276},
{"learn":[4.613805197],"iteration":478,"passed_time":17.45597649,"remaining_time":18.98656316},
{"learn":[4.606989263],"iteration":479,"passed_time":17.49030194,"remaining_time":18.94782711},
{"learn":[4.59769834],"iteration":480,"passed_time":17.52459019,"remaining_time":18.90906925},
{"learn":[4.589487964],"iteration":481,"passed_time":17.55938556,"remaining_time":18.87087494},
{"learn":[4.584089967],"iteration":482,"passed_time":17.59417502,"remaining_time":18.83268838},
{"learn":[4.579476219],"iteration":483,"passed_time":17.62821838,"remaining_time":18.79372042},
{"learn":[4.578262005],"iteration":484,"passed_time":17.66321533,"remaining_time":18.75578535},
{"learn":[4.577649485],"iteration":485,"passed_time":17.70226964,"remaining_time":18.72215349},
{"learn":[4.574836967],"iteration":486,"passed_time":17.73824426,"remaining_time":18.68525524},
{"learn":[4.57374955],"iteration":487,"passed_time":17.77536658,"remaining_time":18.64956494},
{"learn":[4.57269372],"iteration":488,"passed_time":17.81031214,"remaining_time":18.61159408},
{"learn":[4.571404783],"iteration":489,"passed_time":17.84380064,"remaining_time":18.57211904},
{"learn":[4.569934741],"iteration":490,"passed_time":17.87791016,"remaining_time":18.53331216},
{"learn":[4.564393257],"iteration":491,"passed_time":17.91229888,"remaining_time":18.49481266},
{"learn":[4.562953439],"iteration":492,"passed_time":17.94924722,"remaining_time":18.45896215},
{"learn":[4.562234502],"iteration":493,"passed_time":17.9850183,"remaining_time":18.42190133},
{"learn":[4.557425486],"iteration":494,"passed_time":18.02312722,"remaining_time":18.3872308},
{"learn":[4.551417678],"iteration":495,"passed_time":18.0616154,"remaining_time":18.35293178},
{"learn":[4.54237675],"iteration":496,"passed_time":18.09977973,"remaining_time":18.31828814},
{"learn":[4.535871291],"iteration":497,"passed_time":18.14181611,"remaining_time":18.28753351},
{"learn":[4.525098806],"iteration":498,"passed_time":18.18260396,"remaining_time":18.25548013},
{"learn":[4.518576353],"iteration":499,"passed_time":18.2207577,"remaining_time":18.2207577},
{"learn":[4.51375256],"iteration":500,"passed_time":18.25877483,"remaining_time":18.18588551},
{"learn":[4.50916989],"iteration":501,"passed_time":18.29527663,"remaining_time":18.14949753},
{"learn":[4.5083355],"iteration":502,"passed_time":18.3316056,"remaining_time":18.11293834},
{"learn":[4.501703005],"iteration":503,"passed_time":18.37208654,"remaining_time":18.08046612},
{"learn":[4.500829291],"iteration":504,"passed_time":18.41060282,"remaining_time":18.04603643},
{"learn":[4.498977937],"iteration":505,"passed_time":18.44748383,"remaining_time":18.00999409},
{"learn":[4.494340765],"iteration":506,"passed_time":18.48558327,"remaining_time":17.97513324},
{"learn":[4.491791521],"iteration":507,"passed_time":18.52270263,"remaining_time":17.93931042},
{"learn":[4.485613035],"iteration":508,"passed_time":18.56021018,"remaining_time":17.90385697},
{"learn":[4.484213763],"iteration":509,"passed_time":18.59990901,"remaining_time":17.87050082},
{"learn":[4.477141784],"iteration":510,"passed_time":18.64007273,"remaining_time":17.83756471},
{"learn":[4.476066782],"iteration":511,"passed_time":18.67816361,"remaining_time":17.80262469},
{"learn":[4.471558106],"iteration":512,"passed_time":18.71782307,"remaining_time":17.76916147},
{"learn":[4.47074503],"iteration":513,"passed_time":18.75727086,"remaining_time":17.73547401},
{"learn":[4.466133864],"iteration":514,"passed_time":18.79229277,"remaining_time":17.69759611},
{"learn":[4.460054292],"iteration":515,"passed_time":18.82973312,"remaining_time":17.66199773},
{"learn":[4.459537982],"iteration":516,"passed_time":18.86808885,"remaining_time":17.62724741},
{"learn":[4.45092915],"iteration":517,"passed_time":18.90703791,"remaining_time":17.59303527},
{"learn":[4.444182948],"iteration":518,"passed_time":18.94758032,"remaining_time":17.56028156},
{"learn":[4.438952359],"iteration":519,"passed_time":18.9852632,"remaining_time":17.52485834},
{"learn":[4.432595588],"iteration":520,"passed_time":19.02324045,"remaining_time":17.48969707},
{"learn":[4.427995076],"iteration":521,"passed_time":19.0614135,"remaining_time":17.45470432},
{"learn":[4.423532596],"iteration":522,"passed_time":19.09719469,"remaining_time":17.41751791},
{"learn":[4.417681771],"iteration":523,"passed_time":19.13500286,"remaining_time":17.38217817},
{"learn":[4.409358599],"iteration":524,"passed_time":19.17429576,"remaining_time":17.34817236},
{"learn":[4.403878937],"iteration":525,"passed_time":19.21388252,"remaining_time":17.31441125},
{"learn":[4.40295802],"iteration":526,"passed_time":19.250371,"remaining_time":17.27784722},
{"learn":[4.396318516],"iteration":527,"passed_time":19.29007747,"remaining_time":17.24416016},
{"learn":[4.394083034],"iteration":528,"passed_time":19.32830384,"remaining_time":17.20913253},
{"learn":[4.393106326],"iteration":529,"passed_time":19.36392588,"remaining_time":17.17178333},
{"learn":[4.392269065],"iteration":530,"passed_time":19.40006433,"remaining_time":17.13489674},
{"learn":[4.385530819],"iteration":531,"passed_time":19.43794553,"remaining_time":17.09954607},
{"learn":[4.379440035],"iteration":532,"passed_time":19.47963979,"remaining_time":17.0675268},
{"learn":[4.375595007],"iteration":533,"passed_time":19.51833373,"remaining_time":17.03285303},
{"learn":[4.374972938],"iteration":534,"passed_time":19.55762169,"remaining_time":16.99868053},
{"learn":[4.367022721],"iteration":535,"passed_time":19.59495631,"remaining_time":16.962798},
{"learn":[4.359917439],"iteration":536,"passed_time":19.63226301,"remaining_time":16.92688598},
{"learn":[4.355227531],"iteration":537,"passed_time":19.66953307,"remaining_time":16.89093732},
{"learn":[4.351233251],"iteration":538,"passed_time":19.70761906,"remaining_time":16.85568161},
{"learn":[4.346895646],"iteration":539,"passed_time":19.74419282,"remaining_time":16.81912721},
{"learn":[4.339069458],"iteration":540,"passed_time":19.78101432,"remaining_time":16.78278295},
{"learn":[4.333370584],"iteration":541,"passed_time":19.8191728,"remaining_time":16.74756669},
{"learn":[4.332816732],"iteration":542,"passed_time":19.85848825,"remaining_time":16.71331331},
{"learn":[4.328123187],"iteration":543,"passed_time":19.89758066,"remaining_time":16.67885437},
{"learn":[4.322114948],"iteration":544,"passed_time":19.93697213,"remaining_time":16.64462811},
{"learn":[4.31649037],"iteration":545,"passed_time":19.97545719,"remaining_time":16.60962924},
{"learn":[4.311810336],"iteration":546,"passed_time":20.0133438,"remaining_time":16.57412201},
{"learn":[4.309511108],"iteration":547,"passed_time":20.04767375,"remaining_time":16.53567251},
{"learn":[4.303035975],"iteration":548,"passed_time":20.08370361,"remaining_time":16.49863448},
{"learn":[4.30176236],"iteration":549,"passed_time":20.12011005,"remaining_time":16.46190822},
{"learn":[4.294138818],"iteration":550,"passed_time":20.15881159,"remaining_time":16.42705337},
{"learn":[4.290811159],"iteration":551,"passed_time":20.19932386,"remaining_time":16.39365415},
{"learn":[4.287606623],"iteration":552,"passed_time":20.23703755,"remaining_time":16.35796706},
{"learn":[4.284507492],"iteration":553,"passed_time":20.27557355,"remaining_time":16.32293466},
{"learn":[4.275581992],"iteration":554,"passed_time":20.31534019,"remaining_time":16.28887637},
{"learn":[4.274245733],"iteration":555,"passed_time":20.35335689,"remaining_time":16.2534001},
{"learn":[4.269677154],"iteration":556,"passed_time":20.39099217,"remaining_time":16.21761137},
{"learn":[4.265264998],"iteration":557,"passed_time":20.42878092,"remaining_time":16.18193757},
{"learn":[4.260135769],"iteration":558,"passed_time":20.48019321,"remaining_time":16.15700395},
{"learn":[4.255428791],"iteration":559,"passed_time":20.51778151,"remaining_time":16.12111405},
{"learn":[4.247707101],"iteration":560,"passed_time":20.55535386,"remaining_time":16.08520561},
{"learn":[4.247222404],"iteration":561,"passed_time":20.59103083,"remaining_time":16.04781406},
{"learn":[4.243274744],"iteration":562,"passed_time":20.62874403,"remaining_time":16.01200913},
{"learn":[4.239432024],"iteration":563,"passed_time":20.66788296,"remaining_time":15.9772996},
{"learn":[4.238122847],"iteration":564,"passed_time":20.70726197,"remaining_time":15.94275922},
{"learn":[4.2351458],"iteration":565,"passed_time":20.74470962,"remaining_time":15.9067208},
{"learn":[4.23134891],"iteration":566,"passed_time":20.78011636,"remaining_time":15.86911884},
{"learn":[4.230689273],"iteration":567,"passed_time":20.81759387,"remaining_time":15.83309957},
{"learn":[4.230085507],"iteration":568,"passed_time":20.85567532,"remaining_time":15.79753262},
{"learn":[4.228697755],"iteration":569,"passed_time":20.89158305,"remaining_time":15.76031704},
{"learn":[4.224016323],"iteration":570,"passed_time":20.92786503,"remaining_time":15.72338721},
{"learn":[4.222974373],"iteration":571,"passed_time":20.96293096,"remaining_time":15.68554974},
{"learn":[4.221725384],"iteration":572,"passed_time":20.99906321,"remaining_time":15.64851656},
{"learn":[4.220175382],"iteration":573,"passed_time":21.03588133,"remaining_time":15.61199555},
{"learn":[4.212600905],"iteration":574,"passed_time":21.07534454,"remaining_time":15.57742858},
{"learn":[4.210933863],"iteration":575,"passed_time":21.11315508,"remaining_time":15.54162805},
{"learn":[4.20461819],"iteration":576,"passed_time":21.15227582,"remaining_time":15.50678106},
{"learn":[4.199453493],"iteration":577,"passed_time":21.19078817,"remaining_time":15.4714751},
{"learn":[4.194526167],"iteration":578,"passed_time":21.22796597,"remaining_time":15.43518769},
{"learn":[4.188936621],"iteration":579,"passed_time":21.26286701,"remaining_time":15.39724852},
{"learn":[4.188351875],"iteration":580,"passed_time":21.29931693,"remaining_time":15.36043682},
{"learn":[4.183962432],"iteration":581,"passed_time":21.33662098,"remaining_time":15.32423981},
{"learn":[4.183662822],"iteration":582,"passed_time":21.37164144,"remaining_time":15.28640563},
{"learn":[4.180423172],"iteration":583,"passed_time":21.40825216,"remaining_time":15.24971386},
{"learn":[4.179831801],"iteration":584,"passed_time":21.44485467,"remaining_time":15.21301656},
{"learn":[4.176452328],"iteration":585,"passed_time":21.48240347,"remaining_time":15.17698812},
{"learn":[4.17574982],"iteration":586,"passed_time":21.51793295,"remaining_time":15.13953375},
{"learn":[4.17502966],"iteration":587,"passed_time":21.55588631,"remaining_time":15.10378428},
{"learn":[4.173021162],"iteration":588,"passed_time":21.59177599,"remaining_time":15.06658732},
{"learn":[4.172548787],"iteration":589,"passed_time":21.62725014,"remaining_time":15.02910603},
{"learn":[4.172078988],"iteration":590,"passed_time":21.66396679,"remaining_time":14.9924914},
{"learn":[4.167159974],"iteration":591,"passed_time":21.70041539,"remaining_time":14.95569169},
{"learn":[4.163060594],"iteration":592,"passed_time":21.73749676,"remaining_time":14.91932745},
{"learn":[4.162676526],"iteration":593,"passed_time":21.77603315,"remaining_time":14.88395532},
{"learn":[4.157930761],"iteration":594,"passed_time":21.81345605,"remaining_time":14.84781462},
{"learn":[4.151798489],"iteration":595,"passed_time":21.85187256,"remaining_time":14.81234314},
{"learn":[4.149381081],"iteration":596,"passed_time":21.88907063,"remaining_time":14.77603931},
{"learn":[4.14334253],"iteration":597,"passed_time":21.92473313,"remaining_time":14.7387002},
{"learn":[4.137570441],"iteration":598,"passed_time":21.96219766,"remaining_time":14.70257306},
{"learn":[4.134599919],"iteration":599,"passed_time":21.99988047,"remaining_time":14.66658698},
{"learn":[4.133416645],"iteration":600,"passed_time":22.03641176,"remaining_time":14.62983077},
{"learn":[4.128786562],"iteration":601,"passed_time":22.07395613,"remaining_time":14.59374508},
{"learn":[4.126705019],"iteration":602,"passed_time":22.10979666,"remaining_time":14.55653279},
{"learn":[4.126320488],"iteration":603,"passed_time":22.14622186,"remaining_time":14.51970837},
{"learn":[4.12260985],"iteration":604,"passed_time":22.18317212,"remaining_time":14.48322808},
{"learn":[4.118509652],"iteration":605,"passed_time":22.22133929,"remaining_time":14.44753743},
{"learn":[4.117898723],"iteration":606,"passed_time":22.25820031,"remaining_time":14.41099295},
{"learn":[4.114236685],"iteration":607,"passed_time":22.29541442,"remaining_time":14.37467509},
{"learn":[4.1094627],"iteration":608,"passed_time":22.33290393,"remaining_time":14.33853109},
{"learn":[4.104167808],"iteration":609,"passed_time":22.36896176,"remaining_time":14.30146736},
{"learn":[4.101132302],"iteration":610,"passed_time":22.40690422,"remaining_time":14.26560678},
{"learn":[4.099060298],"iteration":611,"passed_time":22.44510974,"remaining_time":14.22990617},
{"learn":[4.094663996],"iteration":612,"passed_time":22.48183377,"remaining_time":14.1932621},
{"learn":[4.089970292],"iteration":613,"passed_time":22.51954814,"remaining_time":14.15724036},
{"learn":[4.089147212],"iteration":614,"passed_time":22.55645006,"remaining_time":14.12070451},
{"learn":[4.087593362],"iteration":615,"passed_time":22.59223106,"remaining_time":14.08346871},
{"learn":[4.081526627],"iteration":616,"passed_time":22.62849516,"remaining_time":14.04653751},
{"learn":[4.075990509],"iteration":617,"passed_time":22.66768123,"remaining_time":14.01141461},
{"learn":[4.06895269],"iteration":618,"passed_time":22.70492649,"remaining_time":13.97508399},
{"learn":[4.067016965],"iteration":619,"passed_time":22.74208161,"remaining_time":13.93869518},
{"learn":[4.066339143],"iteration":620,"passed_time":22.77736509,"remaining_time":13.90116163},
{"learn":[4.06234303],"iteration":621,"passed_time":22.81547324,"remaining_time":13.8653519},
{"learn":[4.060000457],"iteration":622,"passed_time":22.85552232,"remaining_time":13.83070933},
{"learn":[4.055294118],"iteration":623,"passed_time":22.89808758,"remaining_time":13.7975656},
{"learn":[4.054463899],"iteration":624,"passed_time":22.93456826,"remaining_time":13.76074095},
{"learn":[4.050384052],"iteration":625,"passed_time":22.97208992,"remaining_time":13.72453935},
{"learn":[4.046135118],"iteration":626,"passed_time":23.00818124,"remaining_time":13.68748262},
{"learn":[4.041582063],"iteration":627,"passed_time":23.04598529,"remaining_time":13.65144351},
{"learn":[4.040530289],"iteration":628,"passed_time":23.08382631,"remaining_time":13.6154206},
{"learn":[4.035650135],"iteration":629,"passed_time":23.11928299,"remaining_time":13.5779916},
{"learn":[4.034618074],"iteration":630,"passed_time":23.15483065,"remaining_time":13.54062204},
{"learn":[4.032043749],"iteration":631,"passed_time":23.1918664,"remaining_time":13.50412474},
{"learn":[4.030986305],"iteration":632,"passed_time":23.22949115,"remaining_time":13.46796722},
{"learn":[4.026824549],"iteration":633,"passed_time":23.26691286,"remaining_time":13.43168787},
{"learn":[4.022612034],"iteration":634,"passed_time":23.30495722,"remaining_time":13.39576281},
{"learn":[4.018325208],"iteration":635,"passed_time":23.34106089,"remaining_time":13.35872038},
{"learn":[4.014029352],"iteration":636,"passed_time":23.37615687,"remaining_time":13.32110666},
{"learn":[4.009921638],"iteration":637,"passed_time":23.41332115,"remaining_time":13.28467438},
{"learn":[4.005673888],"iteration":638,"passed_time":23.45128816,"remaining_time":13.24869331},
{"learn":[4.001110119],"iteration":639,"passed_time":23.49047671,"remaining_time":13.21339315},
{"learn":[3.9987638],"iteration":640,"passed_time":23.52854286,"remaining_time":13.17745224},
{"learn":[3.998005536],"iteration":641,"passed_time":23.5636249,"remaining_time":13.13984068},
{"learn":[3.995237756],"iteration":642,"passed_time":23.60132485,"remaining_time":13.10369047},
{"learn":[3.994609879],"iteration":643,"passed_time":23.63700803,"remaining_time":13.06642059},
{"learn":[3.990760401],"iteration":644,"passed_time":23.68428114,"remaining_time":13.03553458},
{"learn":[3.985009084],"iteration":645,"passed_time":23.72143693,"remaining_time":12.99905367},
{"learn":[3.982403025],"iteration":646,"passed_time":23.76077813,"remaining_time":12.96376303},
{"learn":[3.977654429],"iteration":647,"passed_time":23.79855677,"remaining_time":12.92761108},
{"learn":[3.976457329],"iteration":648,"passed_time":23.83605034,"remaining_time":12.89129995},
{"learn":[3.971975242],"iteration":649,"passed_time":23.87133174,"remaining_time":12.85379401},
{"learn":[3.969278397],"iteration":650,"passed_time":23.90833295,"remaining_time":12.8172169},
{"learn":[3.966489247],"iteration":651,"passed_time":23.94634698,"remaining_time":12.78117906},
{"learn":[3.963244283],"iteration":652,"passed_time":23.98336038,"remaining_time":12.74460345},
{"learn":[3.961194188],"iteration":653,"passed_time":24.02103839,"remaining_time":12.70837811},
{"learn":[3.959606504],"iteration":654,"passed_time":24.05726944,"remaining_time":12.67138619},
{"learn":[3.955440987],"iteration":655,"passed_time":24.09254875,"remaining_time":12.63389752},
{"learn":[3.954862226],"iteration":656,"passed_time":24.12905932,"remaining_time":12.59705837},
{"learn":[3.951182796],"iteration":657,"passed_time":24.16480127,"remaining_time":12.55982072},
{"learn":[3.949125392],"iteration":658,"passed_time":24.19935618,"remaining_time":12.52197338},
{"learn":[3.94468549],"iteration":659,"passed_time":24.23866491,"remaining_time":12.48658495},
{"learn":[3.942907502],"iteration":660,"passed_time":24.27663849,"remaining_time":12.45049992},
{"learn":[3.938738741],"iteration":661,"passed_time":24.31366067,"remaining_time":12.41392342},
{"learn":[3.936926378],"iteration":662,"passed_time":24.34851491,"remaining_time":12.37624363},
{"learn":[3.933161973],"iteration":663,"passed_time":24.38491327,"remaining_time":12.33935371},
{"learn":[3.930902776],"iteration":664,"passed_time":24.42151491,"remaining_time":12.30256766},
{"learn":[3.927831562],"iteration":665,"passed_time":24.46038184,"remaining_time":12.26691822},
{"learn":[3.922824325],"iteration":666,"passed_time":24.50275292,"remaining_time":12.23300858},
{"learn":[3.921265569],"iteration":667,"passed_time":24.53762844,"remaining_time":12.19534827},
{"learn":[3.919796957],"iteration":668,"passed_time":24.57227442,"remaining_time":12.15758271},
{"learn":[3.916848357],"iteration":669,"passed_time":24.60838518,"remaining_time":12.12054792},
{"learn":[3.912471302],"iteration":670,"passed_time":24.64565571,"remaining_time":12.08408455},
{"learn":[3.908263952],"iteration":671,"passed_time":24.68302773,"remaining_time":12.0476683},
{"learn":[3.905357633],"iteration":672,"passed_time":24.71968484,"remaining_time":12.01090184},
{"learn":[3.902939252],"iteration":673,"passed_time":24.75578104,"remaining_time":11.97386442},
{"learn":[3.899522859],"iteration":674,"passed_time":24.79097386,"remaining_time":11.93639482},
{"learn":[3.899255112],"iteration":675,"passed_time":24.82704715,"remaining_time":11.89935396},
{"learn":[3.897817812],"iteration":676,"passed_time":24.86338752,"remaining_time":11.86244338},
{"learn":[3.894823811],"iteration":677,"passed_time":24.90225261,"remaining_time":11.82673354},
{"learn":[3.891001845],"iteration":678,"passed_time":24.93964326,"remaining_time":11.79031736},
{"learn":[3.886606129],"iteration":679,"passed_time":24.97752014,"remaining_time":11.75412712},
{"learn":[3.88590803],"iteration":680,"passed_time":25.01305038,"remaining_time":11.7168327},
{"learn":[3.882672667],"iteration":681,"passed_time":25.05051803,"remaining_time":11.68044682},
{"learn":[3.880071488],"iteration":682,"passed_time":25.0873664,"remaining_time":11.64377035},
{"learn":[3.875543012],"iteration":683,"passed_time":25.13655906,"remaining_time":11.61279629},
{"learn":[3.871382737],"iteration":684,"passed_time":25.17330114,"remaining_time":11.57604359},
{"learn":[3.868668287],"iteration":685,"passed_time":25.20876021,"remaining_time":11.53870366},
{"learn":[3.864029478],"iteration":686,"passed_time":25.24513642,"remaining_time":11.50178704},
{"learn":[3.860290944],"iteration":687,"passed_time":25.28205985,"remaining_time":11.46512016},
{"learn":[3.857780771],"iteration":688,"passed_time":25.32140286,"remaining_time":11.42954469},
{"learn":[3.854380358],"iteration":689,"passed_time":25.35703231,"remaining_time":11.39228988},
{"learn":[3.851687095],"iteration":690,"passed_time":25.39431957,"remaining_time":11.35578111},
{"learn":[3.850557093],"iteration":691,"passed_time":25.42857829,"remaining_time":11.31792213},
{"learn":[3.848807032],"iteration":692,"passed_time":25.46536081,"remaining_time":11.28119158},
{"learn":[3.845084284],"iteration":693,"passed_time":25.5028939,"remaining_time":11.24479184},
{"learn":[3.842705962],"iteration":694,"passed_time":25.54037599,"remaining_time":11.20836644},
{"learn":[3.840095443],"iteration":695,"passed_time":25.57839733,"remaining_time":11.17217355},
{"learn":[3.83956284],"iteration":696,"passed_time":25.61263132,"remaining_time":11.13432897},
{"learn":[3.839056546],"iteration":697,"passed_time":25.64999276,"remaining_time":11.09784787},
{"learn":[3.836039228],"iteration":698,"passed_time":25.6869831,"remaining_time":11.06120445},
{"learn":[3.835272095],"iteration":699,"passed_time":25.72241812,"remaining_time":11.02389348},
{"learn":[3.832346609],"iteration":700,"passed_time":25.76948263,"remaining_time":10.99154822},
{"learn":[3.831888703],"iteration":701,"passed_time":25.80525613,"remaining_time":10.95436799},
{"learn":[3.829896709],"iteration":702,"passed_time":25.84256715,"remaining_time":10.91784132},
{"learn":[3.826211784],"iteration":703,"passed_time":25.87906845,"remaining_time":10.88097196},
{"learn":[3.823760937],"iteration":704,"passed_time":25.91557948,"remaining_time":10.84410773},
{"learn":[3.82227624],"iteration":705,"passed_time":25.95091675,"remaining_time":10.8067557},
{"learn":[3.818909141],"iteration":706,"passed_time":25.9889731,"remaining_time":10.77053623},
{"learn":[3.817137818],"iteration":707,"passed_time":26.02569602,"remaining_time":10.73376163},
{"learn":[3.814441583],"iteration":708,"passed_time":26.0632891,"remaining_time":10.69734433},
{"learn":[3.810226613],"iteration":709,"passed_time":26.10112736,"remaining_time":10.66102385},
{"learn":[3.808310156],"iteration":710,"passed_time":26.13849192,"remaining_time":10.62450656},
{"learn":[3.805181273],"iteration":711,"passed_time":26.17563612,"remaining_time":10.58789776},
{"learn":[3.803076208],"iteration":712,"passed_time":26.2137234,"remaining_time":10.55166706},
{"learn":[3.799665534],"iteration":713,"passed_time":26.25446811,"remaining_time":10.51649563},
{"learn":[3.798367449],"iteration":714,"passed_time":26.29159616,"remaining_time":10.479867},
{"learn":[3.794676664],"iteration":715,"passed_time":26.3267459,"remaining_time":10.44245229},
{"learn":[3.792935548],"iteration":716,"passed_time":26.36435668,"remaining_time":10.40601526},
{"learn":[3.790030167],"iteration":717,"passed_time":26.39965131,"remaining_time":10.36866528},
{"learn":[3.789607073],"iteration":718,"passed_time":26.43637841,"remaining_time":10.33188085},
{"learn":[3.789386096],"iteration":719,"passed_time":26.47442244,"remaining_time":10.29560873},
{"learn":[3.788219989],"iteration":720,"passed_time":26.50901087,"remaining_time":10.2579945},
{"learn":[3.786211135],"iteration":721,"passed_time":26.54492483,"remaining_time":10.22089904},
{"learn":[3.783946245],"iteration":722,"passed_time":26.5800667,"remaining_time":10.18351103},
{"learn":[3.780397813],"iteration":723,"passed_time":26.61639146,"remaining_time":10.14658017},
{"learn":[3.777112224],"iteration":724,"passed_time":26.65497068,"remaining_time":10.11050612},
{"learn":[3.775698203],"iteration":725,"passed_time":26.69010683,"remaining_time":10.07312572},
{"learn":[3.775139543],"iteration":726,"passed_time":26.7269121,"remaining_time":10.03637827},
{"learn":[3.77486134],"iteration":727,"passed_time":26.76152938,"remaining_time":9.998813175},
{"learn":[3.772099529],"iteration":728,"passed_time":26.79659698,"remaining_time":9.961423569},
{"learn":[3.768487323],"iteration":729,"passed_time":26.83395704,"remaining_time":9.92488822},
{"learn":[3.766016291],"iteration":730,"passed_time":26.87142658,"remaining_time":9.888390903},
{"learn":[3.762686033],"iteration":731,"passed_time":26.90932773,"remaining_time":9.852048952},
{"learn":[3.758837935],"iteration":732,"passed_time":26.94519577,"remaining_time":9.814962169},
{"learn":[3.757424489],"iteration":733,"passed_time":26.98018774,"remaining_time":9.777561225},
{"learn":[3.755363318],"iteration":734,"passed_time":27.01685462,"remaining_time":9.740770714},
{"learn":[3.753560916],"iteration":735,"passed_time":27.05723497,"remaining_time":9.705312543},
{"learn":[3.751667056],"iteration":736,"passed_time":27.09447411,"remaining_time":9.668720069},
{"learn":[3.75013064],"iteration":737,"passed_time":27.13450313,"remaining_time":9.633116286},
{"learn":[3.747614153],"iteration":738,"passed_time":27.17149119,"remaining_time":9.596426523},
{"learn":[3.745320703],"iteration":739,"passed_time":27.20760836,"remaining_time":9.559429966},
{"learn":[3.74250145],"iteration":740,"passed_time":27.2433886,"remaining_time":9.522318011},
{"learn":[3.739940076],"iteration":741,"passed_time":27.27918797,"remaining_time":9.485216304},
{"learn":[3.737988408],"iteration":742,"passed_time":27.31387807,"remaining_time":9.447734406},
{"learn":[3.735414139],"iteration":743,"passed_time":27.35122428,"remaining_time":9.411173946},
{"learn":[3.735180827],"iteration":744,"passed_time":27.38727243,"remaining_time":9.374167074},
{"learn":[3.733647871],"iteration":745,"passed_time":27.42213738,"remaining_time":9.336759914},
{"learn":[3.73224787],"iteration":746,"passed_time":27.45736155,"remaining_time":9.299481222},
{"learn":[3.730608253],"iteration":747,"passed_time":27.49350613,"remaining_time":9.262518107},
{"learn":[3.727739152],"iteration":748,"passed_time":27.52882559,"remaining_time":9.225280673},
{"learn":[3.725522637],"iteration":749,"passed_time":27.56523473,"remaining_time":9.188411576},
{"learn":[3.723191476],"iteration":750,"passed_time":27.60094358,"remaining_time":9.151311519},
{"learn":[3.720605041],"iteration":751,"passed_time":27.63630401,"remaining_time":9.114100257},
{"learn":[3.719142096],"iteration":752,"passed_time":27.6722445,"remaining_time":9.077084185},
{"learn":[3.715781898],"iteration":753,"passed_time":27.7070024,"remaining_time":9.039685133},
{"learn":[3.715545593],"iteration":754,"passed_time":27.74287243,"remaining_time":9.002653966},
{"learn":[3.713138212],"iteration":755,"passed_time":27.77836958,"remaining_time":8.965505526},
{"learn":[3.710697256],"iteration":756,"passed_time":27.81357894,"remaining_time":8.928269066},
{"learn":[3.710262883],"iteration":757,"passed_time":27.84935312,"remaining_time":8.891218277},
{"learn":[3.708023993],"iteration":758,"passed_time":27.88715631,"remaining_time":8.854815112},
{"learn":[3.704666509],"iteration":759,"passed_time":27.92298383,"remaining_time":8.817784366},
{"learn":[3.70427484],"iteration":760,"passed_time":27.95812473,"remaining_time":8.780541143},
{"learn":[3.701803029],"iteration":761,"passed_time":27.99512399,"remaining_time":8.74388387},
{"learn":[3.700271894],"iteration":762,"passed_time":28.02987652,"remaining_time":8.706527831},
{"learn":[3.697976729],"iteration":763,"passed_time":28.06497271,"remaining_time":8.669284763},
{"learn":[3.695909243],"iteration":764,"passed_time":28.10047584,"remaining_time":8.632172317},
{"learn":[3.695473761],"iteration":765,"passed_time":28.13512855,"remaining_time":8.594804282},
{"learn":[3.695028256],"iteration":766,"passed_time":28.16978545,"remaining_time":8.557444603},
{"learn":[3.692594203],"iteration":767,"passed_time":28.20735793,"remaining_time":8.520972707},
{"learn":[3.690600728],"iteration":768,"passed_time":28.24359607,"remaining_time":8.484097129},
{"learn":[3.690327459],"iteration":769,"passed_time":28.28022647,"remaining_time":8.447340375},
{"learn":[3.686648088],"iteration":770,"passed_time":28.31666499,"remaining_time":8.410526956},
{"learn":[3.685127932],"iteration":771,"passed_time":28.35141199,"remaining_time":8.373214941},
{"learn":[3.684976096],"iteration":772,"passed_time":28.38910265,"remaining_time":8.336773998},
{"learn":[3.683720564],"iteration":773,"passed_time":28.42414571,"remaining_time":8.299556758},
{"learn":[3.683336749],"iteration":774,"passed_time":28.45869347,"remaining_time":8.26220133},
{"learn":[3.681324261],"iteration":775,"passed_time":28.4935319,"remaining_time":8.224937044},
{"learn":[3.679912767],"iteration":776,"passed_time":28.52841168,"remaining_time":8.187690868},
{"learn":[3.677434329],"iteration":777,"passed_time":28.564254,"remaining_time":8.150725435},
{"learn":[3.675190722],"iteration":778,"passed_time":28.60120502,"remaining_time":8.114077419},
{"learn":[3.672406148],"iteration":779,"passed_time":28.63760456,"remaining_time":8.077273082},
{"learn":[3.671799357],"iteration":780,"passed_time":28.67171306,"remaining_time":8.03982735},
{"learn":[3.669813875],"iteration":781,"passed_time":28.70641586,"remaining_time":8.002555827},
{"learn":[3.66882364],"iteration":782,"passed_time":28.74525492,"remaining_time":7.966437186},
{"learn":[3.667677958],"iteration":783,"passed_time":28.78393241,"remaining_time":7.930267093},
{"learn":[3.665487734],"iteration":784,"passed_time":28.8249677,"remaining_time":7.894736377},
{"learn":[3.664077299],"iteration":785,"passed_time":28.86568159,"remaining_time":7.859104147},
{"learn":[3.662570146],"iteration":786,"passed_time":28.90070779,"remaining_time":7.821919643},
{"learn":[3.6622627],"iteration":787,"passed_time":28.9366009,"remaining_time":7.784973847},
{"learn":[3.661164484],"iteration":788,"passed_time":28.97200933,"remaining_time":7.7479011},
{"learn":[3.658782235],"iteration":789,"passed_time":29.00760579,"remaining_time":7.710882551},
{"learn":[3.657259306],"iteration":790,"passed_time":29.04206711,"remaining_time":7.673567668},
{"learn":[3.654489416],"iteration":791,"passed_time":29.07832114,"remaining_time":7.636730804},
{"learn":[3.653033981],"iteration":792,"passed_time":29.11280101,"remaining_time":7.599432293},
{"learn":[3.651726939],"iteration":793,"passed_time":29.14654084,"remaining_time":7.561948884},
{"learn":[3.649702261],"iteration":794,"passed_time":29.18117869,"remaining_time":7.524706455},
{"learn":[3.648024015],"iteration":795,"passed_time":29.21539864,"remaining_time":7.48736347},
{"learn":[3.645143676],"iteration":796,"passed_time":29.25130358,"remaining_time":7.450457499},
{"learn":[3.644792222],"iteration":797,"passed_time":29.28758942,"remaining_time":7.413650455},
{"learn":[3.642399748],"iteration":798,"passed_time":29.32166302,"remaining_time":7.376288194},
{"learn":[3.640825956],"iteration":799,"passed_time":29.3560911,"remaining_time":7.339022774},
{"learn":[3.640510763],"iteration":800,"passed_time":29.39048399,"remaining_time":7.301755697},
{"learn":[3.638667591],"iteration":801,"passed_time":29.42737291,"remaining_time":7.265112015},
{"learn":[3.638276067],"iteration":802,"passed_time":29.4658239,"remaining_time":7.228850944},
{"learn":[3.637381188],"iteration":803,"passed_time":29.50633413,"remaining_time":7.193086431},
{"learn":[3.634612353],"iteration":804,"passed_time":29.54530568,"remaining_time":7.156937401},
{"learn":[3.632687068],"iteration":805,"passed_time":29.58336855,"remaining_time":7.120562654},
{"learn":[3.629814031],"iteration":806,"passed_time":29.62246327,"remaining_time":7.084430497},
{"learn":[3.628013281],"iteration":807,"passed_time":29.66041454,"remaining_time":7.048019296},
{"learn":[3.627065671],"iteration":808,"passed_time":29.70019979,"remaining_time":7.01203728},
{"learn":[3.626195551],"iteration":809,"passed_time":29.73888218,"remaining_time":6.975787177},
{"learn":[3.624300673],"iteration":810,"passed_time":29.77557285,"remaining_time":6.939066915},
{"learn":[3.623507219],"iteration":811,"passed_time":29.81373817,"remaining_time":6.902688148},
{"learn":[3.622168258],"iteration":812,"passed_time":29.85132039,"remaining_time":6.866170864},
{"learn":[3.621942236],"iteration":813,"passed_time":29.88800698,"remaining_time":6.829446313},
{"learn":[3.619512365],"iteration":814,"passed_time":29.92610996,"remaining_time":6.793043365},
{"learn":[3.61792341],"iteration":815,"passed_time":29.96549129,"remaining_time":6.756924505},
{"learn":[3.61628546],"iteration":816,"passed_time":30.00298915,"remaining_time":6.720375783},
{"learn":[3.613672631],"iteration":817,"passed_time":30.04275243,"remaining_time":6.68432878},
{"learn":[3.612215464],"iteration":818,"passed_time":30.08188083,"remaining_time":6.648132394},
{"learn":[3.611045465],"iteration":819,"passed_time":30.12010734,"remaining_time":6.61173088},
{"learn":[3.608533949],"iteration":820,"passed_time":30.16103236,"remaining_time":6.575913267},
{"learn":[3.60821101],"iteration":821,"passed_time":30.19991237,"remaining_time":6.539640392},
{"learn":[3.607192916],"iteration":822,"passed_time":30.23961699,"remaining_time":6.503538526},
{"learn":[3.606050843],"iteration":823,"passed_time":30.28068537,"remaining_time":6.467719205},
{"learn":[3.604720051],"iteration":824,"passed_time":30.31848251,"remaining_time":6.431193259},
{"learn":[3.602402342],"iteration":825,"passed_time":30.3567113,"remaining_time":6.394755165},
{"learn":[3.602024768],"iteration":826,"passed_time":30.39696379,"remaining_time":6.358736077},
{"learn":[3.60115692],"iteration":827,"passed_time":30.43519146,"remaining_time":6.322286149},
{"learn":[3.59926481],"iteration":828,"passed_time":30.47282028,"remaining_time":6.285708405},
{"learn":[3.5975967],"iteration":829,"passed_time":30.51132869,"remaining_time":6.249308287},
{"learn":[3.596254114],"iteration":830,"passed_time":30.54931932,"remaining_time":6.212797792},
{"learn":[3.595235268],"iteration":831,"passed_time":30.58739138,"remaining_time":6.176300183},
{"learn":[3.593057166],"iteration":832,"passed_time":30.63102996,"remaining_time":6.140914769},
{"learn":[3.591603714],"iteration":833,"passed_time":30.67056488,"remaining_time":6.10469277},
{"learn":[3.589992336],"iteration":834,"passed_time":30.70862104,"remaining_time":6.068170624},
{"learn":[3.587261351],"iteration":835,"passed_time":30.74531002,"remaining_time":6.031376607},
{"learn":[3.585791333],"iteration":836,"passed_time":30.77845926,"remaining_time":5.993893499},
{"learn":[3.58416442],"iteration":837,"passed_time":30.81669897,"remaining_time":5.957404813},
{"learn":[3.582224023],"iteration":838,"passed_time":30.85928082,"remaining_time":5.921745187},
{"learn":[3.579912193],"iteration":839,"passed_time":30.89586167,"remaining_time":5.884926032},
{"learn":[3.57853153],"iteration":840,"passed_time":30.93029666,"remaining_time":5.847701747},
{"learn":[3.576649864],"iteration":841,"passed_time":30.96505788,"remaining_time":5.810545302},
{"learn":[3.575057984],"iteration":842,"passed_time":30.99946929,"remaining_time":5.773329394},
{"learn":[3.573470946],"iteration":843,"passed_time":31.03461401,"remaining_time":5.73625567},
{"learn":[3.57222825],"iteration":844,"passed_time":31.06963909,"remaining_time":5.699164566},
{"learn":[3.571427398],"iteration":845,"passed_time":31.10533921,"remaining_time":5.662201228},
{"learn":[3.570199688],"iteration":846,"passed_time":31.13911884,"remaining_time":5.624893957},
{"learn":[3.569844924],"iteration":847,"passed_time":31.17256633,"remaining_time":5.587535474},
{"learn":[3.569715908],"iteration":848,"passed_time":31.2063737,"remaining_time":5.550250211},
{"learn":[3.568013702],"iteration":849,"passed_time":31.24070289,"remaining_time":5.513065216},
{"learn":[3.567053269],"iteration":850,"passed_time":31.2750944,"remaining_time":5.475897845},
{"learn":[3.566490579],"iteration":851,"passed_time":31.31028332,"remaining_time":5.438875507},
{"learn":[3.564982623],"iteration":852,"passed_time":31.34531994,"remaining_time":5.401831221},
{"learn":[3.564820406],"iteration":853,"passed_time":31.37879651,"remaining_time":5.364524931},
{"learn":[3.563207119],"iteration":854,"passed_time":31.41279952,"remaining_time":5.327316878},
{"learn":[3.561869915],"iteration":855,"passed_time":31.44707936,"remaining_time":5.290162882},
{"learn":[3.561541623],"iteration":856,"passed_time":31.48113655,"remaining_time":5.252978445},
{"learn":[3.560340008],"iteration":857,"passed_time":31.51530077,"remaining_time":5.215819008},
{"learn":[3.559018046],"iteration":858,"passed_time":31.55191279,"remaining_time":5.179068339},
{"learn":[3.558703852],"iteration":859,"passed_time":31.58521452,"remaining_time":5.141779108},
{"learn":[3.556566975],"iteration":860,"passed_time":31.62055131,"remaining_time":5.104827679},
{"learn":[3.554838453],"iteration":861,"passed_time":31.65523392,"remaining_time":5.067775268},
{"learn":[3.554423477],"iteration":862,"passed_time":31.68899031,"remaining_time":5.030581313},
{"learn":[3.55415562],"iteration":863,"passed_time":31.72269939,"remaining_time":4.993387867},
{"learn":[3.552778074],"iteration":864,"passed_time":31.75852421,"remaining_time":4.956532681},
{"learn":[3.550689484],"iteration":865,"passed_time":31.79359087,"remaining_time":4.91956256},
{"learn":[3.549054018],"iteration":866,"passed_time":31.82779426,"remaining_time":4.882464402},
{"learn":[3.548804519],"iteration":867,"passed_time":31.86142247,"remaining_time":4.845285444},
{"learn":[3.547556875],"iteration":868,"passed_time":31.89519506,"remaining_time":4.808136424},
{"learn":[3.547437325],"iteration":869,"passed_time":31.92861459,"remaining_time":4.77094241},
{"learn":[3.546548823],"iteration":870,"passed_time":31.96325007,"remaining_time":4.733937151},
{"learn":[3.544922823],"iteration":871,"passed_time":31.99962836,"remaining_time":4.697193154},
{"learn":[3.543975511],"iteration":872,"passed_time":32.0338074,"remaining_time":4.660130058},
{"learn":[3.542632816],"iteration":873,"passed_time":32.06789698,"remaining_time":4.623060664},
{"learn":[3.541794624],"iteration":874,"passed_time":32.1022248,"remaining_time":4.586032114},
{"learn":[3.540551374],"iteration":875,"passed_time":32.13641188,"remaining_time":4.54898981},
{"learn":[3.540206017],"iteration":876,"passed_time":32.17052012,"remaining_time":4.511942959},
{"learn":[3.538635859],"iteration":877,"passed_time":32.20625951,"remaining_time":4.475129454},
{"learn":[3.538335102],"iteration":878,"passed_time":32.24014009,"remaining_time":4.438062515},
{"learn":[3.536280942],"iteration":879,"passed_time":32.2752727,"remaining_time":4.40117355},
{"learn":[3.535863379],"iteration":880,"passed_time":32.30879553,"remaining_time":4.364071133},
{"learn":[3.5344482],"iteration":881,"passed_time":32.34269405,"remaining_time":4.327027095},
{"learn":[3.534051953],"iteration":882,"passed_time":32.37633257,"remaining_time":4.289955731},
{"learn":[3.533594009],"iteration":883,"passed_time":32.41280716,"remaining_time":4.253264288},
{"learn":[3.531843445],"iteration":884,"passed_time":32.44805937,"remaining_time":4.216414494},
{"learn":[3.531697853],"iteration":885,"passed_time":32.48180042,"remaining_time":4.179373869},
{"learn":[3.530046181],"iteration":886,"passed_time":32.51650493,"remaining_time":4.142463424},
{"learn":[3.528426543],"iteration":887,"passed_time":32.55197959,"remaining_time":4.105655084},
{"learn":[3.526930895],"iteration":888,"passed_time":32.58597656,"remaining_time":4.06866524},
{"learn":[3.526805461],"iteration":889,"passed_time":32.61969252,"remaining_time":4.03164739},
{"learn":[3.525126157],"iteration":890,"passed_time":32.65660721,"remaining_time":3.995028267},
{"learn":[3.523792734],"iteration":891,"passed_time":32.69121,"remaining_time":3.958128565},
{"learn":[3.522004266],"iteration":892,"passed_time":32.72552857,"remaining_time":3.921199951},
{"learn":[3.52106771],"iteration":893,"passed_time":32.75974961,"remaining_time":3.884265614},
{"learn":[3.520725613],"iteration":894,"passed_time":32.7939456,"remaining_time":3.8473344},
{"learn":[3.519524385],"iteration":895,"passed_time":32.82824116,"remaining_time":3.810420849},
{"learn":[3.518384905],"iteration":896,"passed_time":32.86465706,"remaining_time":3.773756608},
{"learn":[3.518036983],"iteration":897,"passed_time":32.89842745,"remaining_time":3.736792428},
{"learn":[3.516644657],"iteration":898,"passed_time":32.93263528,"remaining_time":3.699884498},
{"learn":[3.515000839],"iteration":899,"passed_time":32.96643882,"remaining_time":3.662937647},
{"learn":[3.513195579],"iteration":900,"passed_time":33.00104251,"remaining_time":3.626085692},
{"learn":[3.512123158],"iteration":901,"passed_time":33.03531273,"remaining_time":3.589202492},
{"learn":[3.511814694],"iteration":902,"passed_time":33.0693747,"remaining_time":3.552302708},
{"learn":[3.510976077],"iteration":903,"passed_time":33.12134366,"remaining_time":3.517310832},
{"learn":[3.509386049],"iteration":904,"passed_time":33.15416525,"remaining_time":3.48027149},
{"learn":[3.509074906],"iteration":905,"passed_time":33.1867035,"remaining_time":3.443212062},
{"learn":[3.508953029],"iteration":906,"passed_time":33.22008955,"remaining_time":3.406249535},
{"learn":[3.507731372],"iteration":907,"passed_time":33.25522961,"remaining_time":3.369472604},
{"learn":[3.50701112],"iteration":908,"passed_time":33.29030688,"remaining_time":3.332692988},
{"learn":[3.506888334],"iteration":909,"passed_time":33.32469157,"remaining_time":3.295848617},
{"learn":[3.506607513],"iteration":910,"passed_time":33.3579669,"remaining_time":3.258901267},
{"learn":[3.50496172],"iteration":911,"passed_time":33.39238924,"remaining_time":3.222072646},
{"learn":[3.503706548],"iteration":912,"passed_time":33.42750103,"remaining_time":3.185314994},
{"learn":[3.503632089],"iteration":913,"passed_time":33.46126856,"remaining_time":3.14843446},
{"learn":[3.50352331],"iteration":914,"passed_time":33.49510441,"remaining_time":3.111567076},
{"learn":[3.502014006],"iteration":915,"passed_time":33.53191869,"remaining_time":3.074979443},
{"learn":[3.501186532],"iteration":916,"passed_time":33.56612418,"remaining_time":3.038155187},
{"learn":[3.500330752],"iteration":917,"passed_time":33.60112885,"remaining_time":3.001408023},
{"learn":[3.499060515],"iteration":918,"passed_time":33.63649217,"remaining_time":2.964696263},
{"learn":[3.498854684],"iteration":919,"passed_time":33.67053451,"remaining_time":2.927872566},
{"learn":[3.497054729],"iteration":920,"passed_time":33.70495407,"remaining_time":2.891087266},
{"learn":[3.49542822],"iteration":921,"passed_time":33.73924771,"remaining_time":2.854296444},
{"learn":[3.494824765],"iteration":922,"passed_time":33.77565446,"remaining_time":2.817687317},
{"learn":[3.493888099],"iteration":923,"passed_time":33.80992014,"remaining_time":2.780902522},
{"learn":[3.492780699],"iteration":924,"passed_time":33.84489405,"remaining_time":2.744180598},
{"learn":[3.492546005],"iteration":925,"passed_time":33.88083965,"remaining_time":2.707540101},
{"learn":[3.491430943],"iteration":926,"passed_time":33.91747343,"remaining_time":2.670955297},
{"learn":[3.490671626],"iteration":927,"passed_time":33.95316862,"remaining_time":2.634297566},
{"learn":[3.490497083],"iteration":928,"passed_time":33.98874136,"remaining_time":2.597632547},
{"learn":[3.490403128],"iteration":929,"passed_time":34.02566394,"remaining_time":2.56107148},
{"learn":[3.489290168],"iteration":930,"passed_time":34.06064451,"remaining_time":2.524365705},
{"learn":[3.489056591],"iteration":931,"passed_time":34.09578186,"remaining_time":2.487675071},
{"learn":[3.488551319],"iteration":932,"passed_time":34.13025899,"remaining_time":2.450940356},
{"learn":[3.48712435],"iteration":933,"passed_time":34.16674407,"remaining_time":2.414352365},
{"learn":[3.485832284],"iteration":934,"passed_time":34.20218833,"remaining_time":2.377692237},
{"learn":[3.484778595],"iteration":935,"passed_time":34.23981458,"remaining_time":2.341183903},
{"learn":[3.483411302],"iteration":936,"passed_time":34.27484461,"remaining_time":2.304498624},
{"learn":[3.481906416],"iteration":937,"passed_time":34.31131799,"remaining_time":2.267912277},
{"learn":[3.48111344],"iteration":938,"passed_time":34.34726033,"remaining_time":2.231291672},
{"learn":[3.48039046],"iteration":939,"passed_time":34.38275486,"remaining_time":2.194643927},
{"learn":[3.479195243],"iteration":940,"passed_time":34.41785055,"remaining_time":2.157973626},
{"learn":[3.478742071],"iteration":941,"passed_time":34.45246797,"remaining_time":2.121277221},
{"learn":[3.477020326],"iteration":942,"passed_time":34.4867951,"remaining_time":2.084567678},
{"learn":[3.476125404],"iteration":943,"passed_time":34.52396392,"remaining_time":2.048031758},
{"learn":[3.475243708],"iteration":944,"passed_time":34.55969141,"remaining_time":2.011410611},
{"learn":[3.474055185],"iteration":945,"passed_time":34.59605061,"remaining_time":1.974827413},
{"learn":[3.473654714],"iteration":946,"passed_time":34.64508647,"remaining_time":1.938954153},
{"learn":[3.472006533],"iteration":947,"passed_time":34.68231105,"remaining_time":1.902405248},
{"learn":[3.470958807],"iteration":948,"passed_time":34.71867259,"remaining_time":1.865808538},
{"learn":[3.470270373],"iteration":949,"passed_time":34.75499342,"remaining_time":1.82921018},
{"learn":[3.469245058],"iteration":950,"passed_time":34.79080049,"remaining_time":1.792585935},
{"learn":[3.468371043],"iteration":951,"passed_time":34.82582416,"remaining_time":1.755923907},
{"learn":[3.467242631],"iteration":952,"passed_time":34.86507556,"remaining_time":1.719473821},
{"learn":[3.467103186],"iteration":953,"passed_time":34.90276074,"remaining_time":1.682942342},
{"learn":[3.466269731],"iteration":954,"passed_time":34.93815437,"remaining_time":1.646300468},
{"learn":[3.46546543],"iteration":955,"passed_time":34.97422464,"remaining_time":1.609692348},
{"learn":[3.46529804],"iteration":956,"passed_time":35.00881386,"remaining_time":1.573018805},
{"learn":[3.465037789],"iteration":957,"passed_time":35.04346988,"remaining_time":1.536352541},
{"learn":[3.46447524],"iteration":958,"passed_time":35.07876068,"remaining_time":1.49971761},
{"learn":[3.463734546],"iteration":959,"passed_time":35.11560221,"remaining_time":1.463150092},
{"learn":[3.463508063],"iteration":960,"passed_time":35.1516805,"remaining_time":1.42655103},
{"learn":[3.462402902],"iteration":961,"passed_time":35.18860333,"remaining_time":1.38998641},
{"learn":[3.461511274],"iteration":962,"passed_time":35.22569012,"remaining_time":1.353427346},
{"learn":[3.461069026],"iteration":963,"passed_time":35.26106,"remaining_time":1.316803071},
{"learn":[3.460966006],"iteration":964,"passed_time":35.29636603,"remaining_time":1.280179079},
{"learn":[3.460178384],"iteration":965,"passed_time":35.33318436,"remaining_time":1.243611044},
{"learn":[3.45992135],"iteration":966,"passed_time":35.36810342,"remaining_time":1.206977676},
{"learn":[3.459764747],"iteration":967,"passed_time":35.40253489,"remaining_time":1.170331732},
{"learn":[3.458350009],"iteration":968,"passed_time":35.4389309,"remaining_time":1.133753207},
{"learn":[3.458107694],"iteration":969,"passed_time":35.47303238,"remaining_time":1.097104094},
{"learn":[3.457979116],"iteration":970,"passed_time":35.50866837,"remaining_time":1.060506058},
{"learn":[3.457100868],"iteration":971,"passed_time":35.54680795,"remaining_time":1.023982122},
{"learn":[3.456192112],"iteration":972,"passed_time":35.5829836,"remaining_time":0.9874003671},
{"learn":[3.454890916],"iteration":973,"passed_time":35.62104462,"remaining_time":0.9508697741},
{"learn":[3.453896328],"iteration":974,"passed_time":35.65695372,"remaining_time":0.9142808645},
{"learn":[3.452459617],"iteration":975,"passed_time":35.69286465,"remaining_time":0.8776933931},
{"learn":[3.451762908],"iteration":976,"passed_time":35.72940393,"remaining_time":0.8411220987},
{"learn":[3.450649587],"iteration":977,"passed_time":35.76768578,"remaining_time":0.8045900686},
{"learn":[3.450526472],"iteration":978,"passed_time":35.80312528,"remaining_time":0.7679934943},
{"learn":[3.450389158],"iteration":979,"passed_time":35.83829514,"remaining_time":0.7313937784},
{"learn":[3.449319015],"iteration":980,"passed_time":35.87452303,"remaining_time":0.6948174696},
{"learn":[3.447919588],"iteration":981,"passed_time":35.91206756,"remaining_time":0.6582660041},
{"learn":[3.447614344],"iteration":982,"passed_time":35.94933203,"remaining_time":0.6217076749},
{"learn":[3.446889696],"iteration":983,"passed_time":35.98845234,"remaining_time":0.5851780868},
{"learn":[3.446247741],"iteration":984,"passed_time":36.02437364,"remaining_time":0.5485945225},
{"learn":[3.445490563],"iteration":985,"passed_time":36.05990624,"remaining_time":0.5120067823},
{"learn":[3.444747592],"iteration":986,"passed_time":36.09712907,"remaining_time":0.4754434427},
{"learn":[3.443749174],"iteration":987,"passed_time":36.13393859,"remaining_time":0.438873748},
{"learn":[3.442892268],"iteration":988,"passed_time":36.17109583,"remaining_time":0.4023074359},
{"learn":[3.441992298],"iteration":989,"passed_time":36.20960113,"remaining_time":0.3657535467},
{"learn":[3.441711769],"iteration":990,"passed_time":36.24530709,"remaining_time":0.3291702965},
{"learn":[3.440742356],"iteration":991,"passed_time":36.28252407,"remaining_time":0.2926010006},
{"learn":[3.440135725],"iteration":992,"passed_time":36.31878669,"remaining_time":0.2560236725},
{"learn":[3.439123316],"iteration":993,"passed_time":36.35475525,"remaining_time":0.2194452027},
{"learn":[3.438297865],"iteration":994,"passed_time":36.39145305,"remaining_time":0.1828716233},
{"learn":[3.43795724],"iteration":995,"passed_time":36.42891444,"remaining_time":0.1463008612},
{"learn":[3.43778272],"iteration":996,"passed_time":36.46486525,"remaining_time":0.1097237671},
{"learn":[3.437671668],"iteration":997,"passed_time":36.50072494,"remaining_time":0.07314774538},
{"learn":[3.436322949],"iteration":998,"passed_time":36.53682067,"remaining_time":0.03657339407},
{"learn":[3.435891923],"iteration":999,"passed_time":36.57156068,"remaining_time":0}
]}